{
    "width": 468,
    "height": 681,
    "description": "An illustration of a pink and purple yo-yo; it hangs suspended by a string connected to a pale pink ring. The illustration is made out of a series of triangles of various sizes.",
    "filename": "E_1QiK3UUAQh4g7",
    "extension": "png",
    "tweet_id": 1440397014487867397,
    "retweet_id": 0,
    "quote_id": 0,
    "reply_id": 0,
    "conversation_id": 1440397014487867397,
    "date": "2021-09-21 19:26:24",
    "author": {
        "id": 1328364776725098497,
        "name": "VertexArchive",
        "nick": "NYT Vertex Archive",
        "location": "",
        "date": "2020-11-16 15:50:31",
        "verified": false,
        "protected": false,
        "profile_banner": "",
        "profile_image": "https://pbs.twimg.com/profile_images/1328364966567677952/8HUjF2xI.jpg",
        "favourites_count": 1641,
        "followers_count": 1813,
        "friends_count": 17,
        "listed_count": 3,
        "media_count": 1473,
        "statuses_count": 2229,
        "description": "An UNOFFICIAL archive of the New York Times' Vertex puzzle. This account is not affiliated with the NY Times. I just like the triangles.",
        "url": "http://www.nytimes.com/puzzles/vertex"
    },
    "user": {
        "id": 1328364776725098497,
        "name": "VertexArchive",
        "nick": "NYT Vertex Archive",
        "location": "",
        "date": "2020-11-16 15:50:31",
        "verified": false,
        "protected": false,
        "profile_banner": "",
        "profile_image": "https://pbs.twimg.com/profile_images/1328364966567677952/8HUjF2xI.jpg",
        "favourites_count": 1641,
        "followers_count": 1813,
        "friends_count": 17,
        "listed_count": 3,
        "media_count": 1473,
        "statuses_count": 2229,
        "description": "An UNOFFICIAL archive of the New York Times' Vertex puzzle. This account is not affiliated with the NY Times. I just like the triangles.",
        "url": "http://www.nytimes.com/puzzles/vertex"
    },
    "lang": "en",
    "source": "Twitter Web App",
    "sensitive": false,
    "favorite_count": 4,
    "quote_count": 0,
    "reply_count": 0,
    "retweet_count": 0,
    "bookmark_count": 0,
    "view_count": 0,
    "hashtags": [
        "NYTVertex"
    ],
    "content": "September 21, 2021. Walk the dog. #NYTVertex",
    "count": 2,
    "category": "twitter",
    "subcategory": "timeline",
    "num": 2
}
