{"date": "2024-04-11", "displayDate": "Thursday, April 11", "id": "1482", "palette": ["#ff554d", "#dfd1ff", "#de0d0f", "#83a3cd", "#f37d00", "#f63626", "#ffa613", "#50548a", "#211c28"], "puzzleConstructor": "Burgess Voshell", "shapes": [{"color": "3", "vertices": [0, 1, 2]}, {"color": "1", "vertices": [1, 3, 4]}, {"color": "3", "vertices": [1, 2, 4]}, {"color": "1", "vertices": [0, 2, 5]}, {"color": "1", "vertices": [0, 5, 6]}, {"color": "3", "vertices": [3, 7, 8]}, {"color": "3", "vertices": [7, 8, 9]}, {"color": "7", "vertices": [10, 11, 12]}, {"color": "3", "vertices": [3, 4, 8]}, {"color": "7", "vertices": [13, 14, 15]}, {"color": "8", "vertices": [11, 12, 16]}, {"color": "1", "vertices": [2, 5, 17]}, {"color": "3", "vertices": [2, 4, 17]}, {"color": "1", "vertices": [8, 9, 18]}, {"color": "7", "vertices": [9, 19, 20]}, {"color": "3", "vertices": [9, 18, 20]}, {"color": "1", "vertices": [4, 17, 21]}, {"color": "3", "vertices": [4, 8, 22]}, {"color": "7", "vertices": [4, 21, 22]}, {"color": "7", "vertices": [14, 15, 23]}, {"color": "7", "vertices": [19, 20, 24]}, {"color": "1", "vertices": [8, 18, 25]}, {"color": "1", "vertices": [8, 22, 25]}, {"color": "1", "vertices": [5, 6, 26]}, {"color": "1", "vertices": [5, 17, 26]}, {"color": "8", "vertices": [16, 27, 28]}, {"color": "1", "vertices": [6, 26, 29]}, {"color": "3", "vertices": [18, 20, 30]}, {"color": "7", "vertices": [20, 24, 31]}, {"color": "3", "vertices": [20, 30, 31]}, {"color": "8", "vertices": [27, 28, 32]}, {"color": "8", "vertices": [23, 33, 34]}, {"color": "3", "vertices": [17, 26, 35]}, {"color": "3", "vertices": [17, 21, 35]}, {"color": "1", "vertices": [18, 25, 30]}, {"color": "3", "vertices": [21, 22, 36]}, {"color": "3", "vertices": [21, 35, 36]}, {"color": "1", "vertices": [22, 25, 37]}, {"color": "7", "vertices": [22, 36, 37]}, {"color": "7", "vertices": [24, 31, 38]}, {"color": "8", "vertices": [33, 34, 39]}, {"color": "3", "vertices": [25, 37, 40]}, {"color": "3", "vertices": [25, 30, 40]}, {"color": "7", "vertices": [26, 29, 41]}, {"color": "3", "vertices": [26, 35, 42]}, {"color": "3", "vertices": [26, 41, 42]}, {"color": "3", "vertices": [30, 31, 43]}, {"color": "7", "vertices": [31, 38, 43]}, {"color": "7", "vertices": [30, 40, 43]}, {"color": "1", "vertices": [44, 45, 46]}, {"color": "3", "vertices": [29, 45, 46]}, {"color": "7", "vertices": [36, 37, 47]}, {"color": "3", "vertices": [37, 40, 47]}, {"color": "3", "vertices": [29, 41, 46]}, {"color": "1", "vertices": [44, 46, 48]}, {"color": "7", "vertices": [35, 36, 49]}, {"color": "7", "vertices": [36, 47, 49]}, {"color": "7", "vertices": [40, 43, 50]}, {"color": "7", "vertices": [38, 43, 51]}, {"color": "3", "vertices": [43, 50, 51]}, {"color": "3", "vertices": [40, 47, 52]}, {"color": "7", "vertices": [40, 50, 52]}, {"color": "3", "vertices": [41, 46, 53]}, {"color": "7", "vertices": [41, 42, 53]}, {"color": "1", "vertices": [46, 48, 54]}, {"color": "1", "vertices": [48, 54, 55]}, {"color": "3", "vertices": [46, 53, 54]}, {"color": "1", "vertices": [35, 42, 56]}, {"color": "3", "vertices": [35, 49, 56]}, {"color": "1", "vertices": [42, 53, 56]}, {"color": "1", "vertices": [47, 52, 57]}, {"color": "3", "vertices": [50, 52, 57]}, {"color": "7", "vertices": [47, 49, 58]}, {"color": "1", "isPreDrawn": true, "vertices": [47, 57, 58]}, {"color": "3", "vertices": [53, 54, 59]}, {"color": "1", "vertices": [53, 56, 60]}, {"color": "1", "vertices": [53, 59, 60]}, {"color": "3", "vertices": [49, 56, 58]}, {"color": "1", "vertices": [50, 51, 61]}, {"color": "3", "vertices": [50, 57, 61]}, {"color": "1", "vertices": [54, 55, 62]}, {"color": "7", "vertices": [51, 61, 63]}, {"color": "3", "vertices": [51, 64, 65]}, {"color": "7", "vertices": [51, 63, 65]}, {"color": "3", "vertices": [56, 58, 60]}, {"color": "3", "vertices": [54, 62, 66]}, {"color": "3", "vertices": [54, 59, 66]}, {"color": "3", "vertices": [64, 65, 67]}, {"color": "3", "vertices": [57, 61, 63]}, {"color": "7", "vertices": [59, 66, 68]}, {"color": "1", "vertices": [59, 60, 68]}, {"color": "3", "vertices": [66, 68, 69]}, {"color": "3", "vertices": [65, 67, 70]}, {"color": "3", "vertices": [57, 63, 71]}, {"color": "7", "vertices": [63, 65, 72]}, {"color": "7", "vertices": [63, 71, 72]}, {"color": "7", "vertices": [60, 68, 73]}, {"color": "3", "vertices": [58, 60, 74]}, {"color": "7", "vertices": [60, 73, 74]}, {"color": "1", "vertices": [57, 58, 75]}, {"color": "3", "vertices": [57, 75, 76]}, {"color": "3", "vertices": [57, 71, 76]}, {"color": "1", "vertices": [58, 75, 77]}, {"color": "3", "vertices": [58, 77, 78]}, {"color": "1", "vertices": [58, 74, 78]}, {"color": "3", "vertices": [65, 70, 72]}, {"color": "3", "vertices": [68, 73, 79]}, {"color": "3", "vertices": [68, 69, 79]}, {"color": "1", "vertices": [73, 74, 79]}, {"color": "3", "vertices": [75, 77, 80]}, {"color": "7", "vertices": [75, 76, 81]}, {"color": "7", "vertices": [75, 80, 81]}, {"color": "3", "vertices": [70, 72, 82]}, {"color": "1", "vertices": [74, 78, 79]}, {"color": "7", "vertices": [71, 76, 83]}, {"color": "7", "vertices": [71, 72, 83]}, {"color": "7", "vertices": [77, 80, 84]}, {"color": "7", "vertices": [77, 78, 84]}, {"color": "3", "vertices": [76, 81, 83]}, {"color": "3", "vertices": [72, 83, 85]}, {"color": "3", "vertices": [72, 82, 85]}, {"color": "3", "vertices": [80, 81, 84]}, {"color": "3", "vertices": [81, 83, 86]}, {"color": "1", "vertices": [81, 84, 86]}, {"color": "1", "vertices": [69, 79, 87]}, {"color": "1", "vertices": [84, 86, 88]}, {"color": "1", "vertices": [79, 87, 89]}, {"color": "3", "vertices": [78, 79, 90]}, {"color": "7", "vertices": [79, 89, 90]}, {"color": "8", "vertices": [91, 92, 93]}, {"color": "7", "vertices": [92, 93, 94]}, {"color": "7", "vertices": [78, 84, 90]}, {"color": "1", "vertices": [84, 88, 95]}, {"color": "3", "vertices": [84, 90, 95]}, {"color": "8", "vertices": [94, 96, 97]}, {"color": "8", "vertices": [96, 97, 98]}, {"color": "1", "vertices": [99, 100, 101]}, {"color": "3", "vertices": [100, 101, 102]}, {"color": "3", "vertices": [101, 102, 103]}, {"color": "2", "vertices": [103, 104, 105]}, {"color": "6", "vertices": [104, 105, 106]}, {"color": "1", "vertices": [99, 101, 107]}, {"color": "1", "vertices": [99, 107, 108]}, {"color": "1", "vertices": [101, 107, 109]}, {"color": "7", "vertices": [101, 103, 110]}, {"color": "3", "vertices": [101, 109, 110]}, {"color": "6", "vertices": [105, 106, 111]}, {"color": "0", "vertices": [106, 111, 112]}, {"color": "2", "vertices": [103, 105, 113]}, {"color": "7", "vertices": [103, 110, 113]}, {"color": "3", "vertices": [107, 108, 109]}, {"color": "4", "vertices": [105, 111, 114]}, {"color": "5", "vertices": [105, 113, 114]}, {"color": "3", "vertices": [108, 115, 116]}, {"color": "3", "vertices": [108, 109, 116]}, {"color": "4", "vertices": [111, 114, 117]}, {"color": "0", "vertices": [111, 112, 118]}, {"color": "5", "vertices": [111, 117, 118]}, {"color": "1", "vertices": [109, 116, 119]}, {"color": "3", "vertices": [109, 110, 119]}, {"color": "6", "vertices": [112, 118, 120]}, {"color": "5", "vertices": [115, 121, 122]}, {"color": "6", "vertices": [121, 122, 123]}, {"color": "7", "vertices": [110, 113, 124]}, {"color": "3", "vertices": [110, 119, 124]}, {"color": "5", "vertices": [115, 116, 122]}, {"color": "5", "vertices": [113, 114, 125]}, {"color": "7", "vertices": [113, 124, 125]}, {"color": "5", "vertices": [117, 118, 126]}, {"color": "6", "vertices": [118, 120, 127]}, {"color": "4", "vertices": [118, 127, 128]}, {"color": "4", "vertices": [118, 126, 128]}, {"color": "6", "vertices": [120, 127, 129]}, {"color": "4", "vertices": [114, 117, 130]}, {"color": "5", "vertices": [114, 125, 130]}, {"color": "7", "vertices": [90, 131, 132]}, {"color": "3", "vertices": [131, 132, 133]}, {"color": "6", "vertices": [122, 123, 134]}, {"color": "0", "vertices": [116, 122, 135]}, {"color": "6", "vertices": [122, 134, 135]}, {"color": "7", "vertices": [90, 123, 132]}, {"color": "4", "vertices": [117, 130, 136]}, {"color": "5", "vertices": [117, 126, 136]}, {"color": "1", "vertices": [116, 119, 137]}, {"color": "0", "vertices": [116, 135, 137]}, {"color": "7", "vertices": [123, 132, 138]}, {"color": "7", "vertices": [123, 134, 138]}, {"color": "1", "vertices": [119, 137, 139]}, {"color": "3", "vertices": [119, 124, 139]}, {"color": "6", "vertices": [134, 135, 138]}, {"color": "6", "vertices": [127, 129, 140]}, {"color": "4", "vertices": [127, 140, 141]}, {"color": "4", "vertices": [127, 128, 141]}, {"color": "6", "vertices": [129, 140, 142]}, {"color": "3", "vertices": [132, 133, 143]}, {"color": "8", "vertices": [132, 138, 144]}, {"color": "8", "vertices": [132, 143, 144]}, {"color": "0", "vertices": [135, 137, 145]}, {"color": "5", "vertices": [126, 136, 146]}, {"color": "4", "vertices": [126, 128, 147]}, {"color": "0", "vertices": [135, 145, 148]}, {"color": "6", "vertices": [135, 138, 148]}, {"color": "4", "vertices": [126, 146, 147]}, {"color": "3", "vertices": [137, 139, 145]}, {"color": "7", "vertices": [124, 125, 149]}, {"color": "7", "vertices": [124, 149, 150]}, {"color": "3", "vertices": [124, 139, 150]}, {"color": "0", "vertices": [140, 142, 151]}, {"color": "4", "vertices": [138, 148, 152]}, {"color": "8", "vertices": [138, 144, 152]}, {"color": "5", "vertices": [125, 130, 149]}, {"color": "5", "vertices": [130, 149, 153]}, {"color": "6", "vertices": [130, 136, 154]}, {"color": "6", "vertices": [130, 153, 154]}, {"color": "2", "vertices": [128, 147, 155]}, {"color": "2", "vertices": [128, 155, 156]}, {"color": "2", "vertices": [128, 141, 157]}, {"color": "2", "vertices": [128, 156, 157]}, {"color": "4", "vertices": [140, 141, 158]}, {"color": "0", "vertices": [140, 151, 159]}, {"color": "5", "vertices": [140, 158, 159]}, {"color": "0", "vertices": [136, 146, 160]}, {"color": "0", "vertices": [136, 154, 160]}, {"color": "1", "vertices": [139, 145, 161]}, {"color": "7", "vertices": [139, 150, 161]}, {"color": "4", "vertices": [148, 152, 162]}, {"color": "8", "vertices": [145, 148, 163]}, {"color": "8", "vertices": [148, 162, 163]}, {"color": "4", "vertices": [141, 158, 164]}, {"color": "2", "vertices": [141, 164, 165]}, {"color": "2", "vertices": [141, 157, 165]}, {"color": "6", "vertices": [155, 156, 166]}, {"color": "6", "vertices": [156, 157, 167]}, {"color": "6", "vertices": [156, 166, 167]}, {"color": "7", "vertices": [149, 150, 168]}, {"color": "3", "vertices": [145, 161, 163]}, {"color": "5", "vertices": [149, 153, 168]}, {"color": "4", "vertices": [146, 147, 169]}, {"color": "2", "vertices": [147, 155, 169]}, {"color": "4", "vertices": [144, 152, 162]}, {"color": "5", "vertices": [151, 159, 170]}, {"color": "4", "vertices": [144, 162, 171]}, {"color": "6", "vertices": [146, 169, 172]}, {"color": "6", "vertices": [146, 160, 172]}, {"color": "6", "vertices": [166, 167, 173]}, {"color": "6", "vertices": [157, 167, 174]}, {"color": "8", "vertices": [167, 174, 175]}, {"color": "8", "vertices": [167, 173, 175]}, {"color": "6", "vertices": [157, 165, 174]}, {"color": "5", "vertices": [159, 170, 176]}, {"color": "3", "vertices": [170, 176, 177]}, {"color": "2", "vertices": [155, 169, 178]}, {"color": "6", "vertices": [155, 166, 179]}, {"color": "6", "vertices": [155, 178, 179]}, {"color": "5", "vertices": [158, 159, 180]}, {"color": "2", "vertices": [159, 176, 180]}, {"color": "3", "vertices": [176, 177, 181]}, {"color": "2", "vertices": [169, 172, 178]}, {"color": "8", "vertices": [162, 163, 182]}, {"color": "4", "vertices": [158, 164, 183]}, {"color": "5", "vertices": [158, 180, 184]}, {"color": "5", "vertices": [158, 183, 184]}, {"color": "8", "vertices": [162, 171, 182]}, {"color": "8", "vertices": [150, 168, 185]}, {"color": "8", "vertices": [150, 185, 186]}, {"color": "7", "vertices": [150, 161, 186]}, {"color": "3", "vertices": [161, 163, 187]}, {"color": "3", "vertices": [163, 187, 188]}, {"color": "3", "vertices": [163, 182, 188]}, {"color": "2", "vertices": [176, 180, 189]}, {"color": "7", "vertices": [176, 181, 189]}, {"color": "0", "vertices": [153, 168, 190]}, {"color": "5", "vertices": [168, 185, 190]}, {"color": "6", "vertices": [165, 174, 175]}, {"color": "6", "isPreDrawn": true, "vertices": [153, 154, 191]}, {"color": "6", "vertices": [153, 190, 191]}, {"color": "7", "vertices": [181, 189, 192]}, {"color": "2", "vertices": [164, 165, 193]}, {"color": "4", "vertices": [164, 183, 194]}, {"color": "2", "vertices": [164, 193, 194]}, {"color": "2", "vertices": [165, 175, 195]}, {"color": "2", "vertices": [165, 193, 195]}, {"color": "0", "vertices": [154, 160, 196]}, {"color": "8", "vertices": [166, 179, 197]}, {"color": "0", "vertices": [154, 191, 196]}, {"color": "8", "vertices": [166, 173, 197]}, {"color": "7", "vertices": [161, 186, 187]}, {"color": "6", "vertices": [160, 172, 198]}, {"color": "2", "vertices": [172, 178, 198]}, {"color": "6", "vertices": [178, 179, 199]}, {"color": "2", "vertices": [178, 198, 199]}, {"color": "2", "vertices": [180, 189, 200]}, {"color": "2", "vertices": [180, 184, 200]}, {"color": "6", "vertices": [179, 197, 199]}, {"color": "6", "vertices": [193, 195, 201]}, {"color": "2", "vertices": [193, 194, 202]}, {"color": "6", "vertices": [193, 201, 202]}, {"color": "2", "vertices": [173, 175, 203]}, {"color": "2", "vertices": [175, 195, 203]}, {"color": "6", "vertices": [183, 194, 204]}, {"color": "2", "vertices": [194, 202, 204]}, {"color": "7", "vertices": [189, 192, 200]}, {"color": "6", "vertices": [160, 198, 205]}, {"color": "6", "vertices": [160, 196, 205]}, {"color": "2", "vertices": [173, 197, 206]}, {"color": "2", "vertices": [173, 203, 206]}, {"color": "8", "vertices": [195, 203, 207]}, {"color": "8", "vertices": [195, 201, 207]}, {"color": "7", "vertices": [192, 200, 208]}, {"color": "6", "vertices": [183, 204, 209]}, {"color": "0", "vertices": [183, 184, 210]}, {"color": "0", "vertices": [183, 209, 210]}, {"color": "7", "vertices": [186, 187, 211]}, {"color": "8", "vertices": [185, 186, 212]}, {"color": "8", "vertices": [186, 211, 212]}, {"color": "2", "vertices": [197, 199, 213]}, {"color": "2", "vertices": [197, 206, 213]}, {"color": "2", "vertices": [198, 199, 205]}, {"color": "5", "vertices": [185, 190, 214]}, {"color": "2", "vertices": [185, 212, 214]}, {"color": "8", "vertices": [203, 206, 215]}, {"color": "6", "vertices": [203, 207, 215]}, {"color": "3", "vertices": [187, 188, 216]}, {"color": "7", "vertices": [187, 211, 216]}, {"color": "7", "vertices": [188, 216, 217]}, {"color": "4", "vertices": [190, 191, 218]}, {"color": "4", "vertices": [190, 214, 218]}, {"color": "6", "vertices": [206, 213, 219]}, {"color": "6", "vertices": [201, 207, 220]}, {"color": "6", "vertices": [201, 202, 220]}, {"color": "2", "vertices": [199, 205, 213]}, {"color": "8", "vertices": [206, 215, 221]}, {"color": "6", "vertices": [206, 219, 221]}, {"color": "2", "vertices": [202, 204, 222]}, {"color": "2", "vertices": [202, 220, 222]}, {"color": "5", "vertices": [191, 196, 223]}, {"color": "5", "vertices": [191, 218, 223]}, {"color": "6", "vertices": [207, 215, 220]}, {"color": "7", "vertices": [211, 216, 217]}, {"color": "6", "vertices": [204, 209, 222]}, {"color": "2", "vertices": [205, 213, 224]}, {"color": "2", "vertices": [213, 219, 224]}, {"color": "6", "vertices": [196, 205, 224]}, {"color": "5", "vertices": [184, 200, 225]}, {"color": "5", "vertices": [184, 210, 225]}, {"color": "7", "vertices": [211, 217, 226]}, {"color": "8", "vertices": [211, 226, 227]}, {"color": "8", "vertices": [211, 212, 227]}, {"color": "2", "vertices": [212, 214, 228]}, {"color": "4", "vertices": [196, 223, 224]}, {"color": "6", "vertices": [214, 228, 229]}, {"color": "6", "vertices": [214, 218, 229]}, {"color": "7", "vertices": [200, 208, 225]}, {"color": "6", "vertices": [215, 221, 230]}, {"color": "6", "vertices": [215, 220, 230]}, {"color": "2", "vertices": [220, 222, 231]}, {"color": "6", "vertices": [209, 222, 231]}, {"color": "7", "vertices": [208, 225, 232]}, {"color": "0", "vertices": [218, 229, 233]}, {"color": "0", "vertices": [218, 223, 233]}, {"color": "2", "vertices": [220, 230, 234]}, {"color": "2", "vertices": [220, 231, 234]}, {"color": "6", "vertices": [219, 221, 230]}, {"color": "2", "vertices": [219, 224, 230]}, {"color": "6", "vertices": [209, 231, 235]}, {"color": "0", "vertices": [209, 210, 236]}, {"color": "0", "vertices": [209, 235, 236]}, {"color": "6", "vertices": [231, 234, 235]}, {"color": "2", "vertices": [224, 230, 234]}, {"color": "4", "vertices": [223, 224, 237]}, {"color": "4", "vertices": [224, 234, 237]}, {"color": "6", "vertices": [223, 233, 238]}, {"color": "6", "vertices": [223, 237, 238]}, {"color": "5", "vertices": [210, 225, 239]}, {"color": "5", "vertices": [210, 236, 239]}, {"color": "4", "vertices": [234, 237, 240]}, {"color": "4", "vertices": [234, 235, 240]}, {"color": "8", "vertices": [225, 232, 241]}, {"color": "8", "vertices": [225, 239, 241]}, {"color": "6", "vertices": [237, 238, 242]}, {"color": "5", "vertices": [235, 236, 243]}, {"color": "5", "vertices": [235, 240, 243]}, {"color": "6", "vertices": [237, 240, 242]}, {"color": "2", "vertices": [236, 239, 244]}, {"color": "2", "vertices": [236, 243, 244]}, {"color": "6", "vertices": [240, 242, 245]}, {"color": "0", "vertices": [240, 245, 246]}, {"color": "0", "vertices": [240, 243, 246]}, {"color": "8", "vertices": [239, 241, 247]}, {"color": "8", "vertices": [239, 244, 247]}, {"color": "5", "vertices": [243, 246, 248]}, {"color": "5", "vertices": [243, 244, 248]}, {"color": "8", "vertices": [244, 248, 249]}, {"color": "8", "vertices": [244, 247, 249]}], "theme": "Buzz off", "vertices": {"0": {"coordinates": [708, 371], "shapes": ["0", "3", "4"]}, "1": {"coordinates": [723, 408], "shapes": ["0", "1", "2"]}, "10": {"coordinates": [707, 565], "shapes": ["7"]}, "100": {"coordinates": [388, 476], "shapes": ["136", "137"]}, "101": {"coordinates": [376, 480], "shapes": ["136", "137", "138", "141", "143", "144", "145"]}, "102": {"coordinates": [384, 490], "shapes": ["137", "138"]}, "103": {"coordinates": [372, 495], "shapes": ["138", "139", "144", "148", "149"]}, "104": {"coordinates": [381, 504], "shapes": ["139", "140"]}, "105": {"coordinates": [368, 509], "shapes": ["139", "140", "146", "148", "151", "152"]}, "106": {"coordinates": [373, 533], "shapes": ["140", "146", "147"]}, "107": {"coordinates": [370, 471], "shapes": ["141", "142", "143", "150"]}, "108": {"coordinates": [364, 459], "shapes": ["142", "150", "153", "154"]}, "109": {"coordinates": [357, 471], "shapes": ["143", "145", "150", "154", "158", "159"]}, "11": {"coordinates": [701, 587], "shapes": ["7", "10"]}, "110": {"coordinates": [346, 478], "shapes": ["144", "145", "149", "159", "163", "164"]}, "111": {"coordinates": [361, 537], "shapes": ["146", "147", "151", "155", "156", "157"]}, "112": {"coordinates": [354, 604], "shapes": ["147", "156", "160"]}, "113": {"coordinates": [342, 493], "shapes": ["148", "149", "152", "163", "166", "167"]}, "114": {"coordinates": [338, 507], "shapes": ["151", "152", "155", "166", "173", "174"]}, "115": {"coordinates": [345, 426], "shapes": ["153", "161", "165"]}, "116": {"coordinates": [330, 428], "shapes": ["153", "154", "158", "165", "178", "183", "184"]}, "117": {"coordinates": [331, 535], "shapes": ["155", "157", "168", "173", "181", "182"]}, "118": {"coordinates": [342, 608], "shapes": ["156", "157", "160", "168", "169", "170", "171"]}, "119": {"coordinates": [325, 467], "shapes": ["158", "159", "164", "183", "187", "188"]}, "12": {"coordinates": [688, 568], "shapes": ["7", "10"]}, "120": {"coordinates": [341, 653], "shapes": ["160", "169", "172"]}, "121": {"coordinates": [348, 413], "shapes": ["161", "162"]}, "122": {"coordinates": [334, 415], "shapes": ["161", "162", "165", "177", "178", "179"]}, "123": {"coordinates": [327, 393], "shapes": ["162", "177", "180", "185", "186"]}, "124": {"coordinates": [303, 471], "shapes": ["163", "164", "167", "188", "204", "205", "206"]}, "125": {"coordinates": [300, 485], "shapes": ["166", "167", "174", "204", "210"]}, "126": {"coordinates": [311, 606], "shapes": ["168", "171", "182", "198", "199", "202"]}, "127": {"coordinates": [316, 706], "shapes": ["169", "170", "172", "190", "191", "192"]}, "128": {"coordinates": [291, 684], "shapes": ["170", "171", "192", "199", "214", "215", "216", "217"]}, "129": {"coordinates": [315, 750], "shapes": ["172", "190", "193"]}, "13": {"coordinates": [702, 266], "shapes": ["9"]}, "130": {"coordinates": [296, 499], "shapes": ["173", "174", "181", "210", "211", "212", "213"]}, "131": {"coordinates": [337, 357], "shapes": ["175", "176"]}, "132": {"coordinates": [313, 356], "shapes": ["175", "176", "180", "185", "194", "195", "196"]}, "133": {"coordinates": [308, 344], "shapes": ["176", "194"]}, "134": {"coordinates": [324, 405], "shapes": ["177", "179", "186", "189"]}, "135": {"coordinates": [311, 411], "shapes": ["178", "179", "184", "189", "197", "200", "201"]}, "136": {"coordinates": [288, 527], "shapes": ["181", "182", "198", "212", "221", "222"]}, "137": {"coordinates": [308, 424], "shapes": ["183", "184", "187", "197", "203"]}, "138": {"coordinates": [301, 403], "shapes": ["185", "186", "189", "195", "201", "208", "209"]}, "139": {"coordinates": [282, 458], "shapes": ["187", "188", "203", "206", "223", "224"]}, "14": {"coordinates": [689, 284], "shapes": ["9", "19"]}, "140": {"coordinates": [289, 804], "shapes": ["190", "191", "193", "207", "218", "219", "220"]}, "141": {"coordinates": [278, 731], "shapes": ["191", "192", "216", "218", "228", "229", "230"]}, "142": {"coordinates": [302, 800], "shapes": ["193", "207"]}, "143": {"coordinates": [285, 343], "shapes": ["194", "196"]}, "144": {"coordinates": [275, 380], "shapes": ["195", "196", "209", "239", "241"]}, "145": {"coordinates": [277, 416], "shapes": ["197", "200", "203", "223", "226", "235"]}, "146": {"coordinates": [269, 598], "shapes": ["198", "202", "221", "237", "242", "243"]}, "147": {"coordinates": [276, 639], "shapes": ["199", "202", "214", "237", "238"]}, "148": {"coordinates": [280, 403], "shapes": ["200", "201", "208", "225", "226", "227"]}, "149": {"coordinates": [277, 479], "shapes": ["204", "205", "210", "211", "234", "236"]}, "15": {"coordinates": [684, 262], "shapes": ["9", "19"]}, "150": {"coordinates": [257, 458], "shapes": ["205", "206", "224", "234", "263", "264", "265"]}, "151": {"coordinates": [275, 898], "shapes": ["207", "219", "240"]}, "152": {"coordinates": [272, 391], "shapes": ["208", "209", "225", "239"]}, "153": {"coordinates": [250, 487], "shapes": ["211", "213", "236", "271", "274", "275"]}, "154": {"coordinates": [242, 515], "shapes": ["212", "213", "222", "274", "282", "284"]}, "155": {"coordinates": [265, 647], "shapes": ["214", "215", "231", "238", "251", "252", "253"]}, "156": {"coordinates": [277, 685], "shapes": ["215", "217", "231", "232", "233"]}, "157": {"coordinates": [266, 724], "shapes": ["216", "217", "230", "232", "245", "248"]}, "158": {"coordinates": [259, 802], "shapes": ["218", "220", "228", "254", "259", "260", "261"]}, "159": {"coordinates": [264, 900], "shapes": ["219", "220", "240", "249", "254", "255"]}, "16": {"coordinates": [682, 588], "shapes": ["10", "25"]}, "160": {"coordinates": [223, 586], "shapes": ["221", "222", "243", "282", "287", "302", "303"]}, "161": {"coordinates": [241, 445], "shapes": ["223", "224", "235", "265", "266", "286"]}, "162": {"coordinates": [259, 394], "shapes": ["225", "227", "239", "241", "258", "262"]}, "163": {"coordinates": [255, 408], "shapes": ["226", "227", "235", "258", "266", "267", "268"]}, "164": {"coordinates": [243, 763], "shapes": ["228", "229", "259", "277", "278", "279"]}, "165": {"coordinates": [243, 746], "shapes": ["229", "230", "248", "273", "277", "280", "281"]}, "166": {"coordinates": [242, 664], "shapes": ["231", "233", "244", "252", "283", "285"]}, "167": {"coordinates": [268, 699], "shapes": ["232", "233", "244", "245", "246", "247"]}, "168": {"coordinates": [253, 472], "shapes": ["234", "236", "263", "271", "272"]}, "169": {"coordinates": [261, 629], "shapes": ["237", "238", "242", "251", "257"]}, "17": {"coordinates": [671, 401], "shapes": ["11", "12", "16", "24", "32", "33"]}, "170": {"coordinates": [266, 933], "shapes": ["240", "249", "250"]}, "171": {"coordinates": [247, 386], "shapes": ["241", "262"]}, "172": {"coordinates": [240, 614], "shapes": ["242", "243", "257", "287", "288"]}, "173": {"coordinates": [223, 677], "shapes": ["244", "247", "285", "297", "304", "305"]}, "174": {"coordinates": [251, 719], "shapes": ["245", "246", "248", "273"]}, "175": {"coordinates": [227, 692], "shapes": ["246", "247", "273", "280", "297", "298"]}, "176": {"coordinates": [254, 937], "shapes": ["249", "250", "255", "256", "269", "270"]}, "177": {"coordinates": [262, 947], "shapes": ["250", "256"]}, "178": {"coordinates": [237, 628], "shapes": ["251", "253", "257", "288", "289", "290"]}, "179": {"coordinates": [232, 643], "shapes": ["252", "253", "283", "289", "293"]}, "18": {"coordinates": [671, 502], "shapes": ["13", "15", "21", "27", "34"]}, "180": {"coordinates": [236, 889], "shapes": ["254", "255", "260", "269", "291", "292"]}, "181": {"coordinates": [250, 951], "shapes": ["256", "270", "276"]}, "182": {"coordinates": [244, 399], "shapes": ["258", "262", "268"]}, "183": {"coordinates": [217, 794], "shapes": ["259", "261", "278", "299", "309", "310", "311"]}, "184": {"coordinates": [197, 869], "shapes": ["260", "261", "292", "310", "343", "344"]}, "185": {"coordinates": [213, 458], "shapes": ["263", "264", "272", "313", "318", "319"]}, "186": {"coordinates": [217, 444], "shapes": ["264", "265", "286", "312", "313", "314"]}, "187": {"coordinates": [211, 432], "shapes": ["266", "267", "286", "312", "322", "323"]}, "188": {"coordinates": [211, 417], "shapes": ["267", "268", "322", "324"]}, "189": {"coordinates": [224, 935], "shapes": ["269", "270", "276", "291", "301"]}, "19": {"coordinates": [688, 537], "shapes": ["14", "20"]}, "190": {"coordinates": [209, 472], "shapes": ["271", "272", "275", "318", "325", "326"]}, "191": {"coordinates": [201, 500], "shapes": ["274", "275", "284", "325", "335", "336"]}, "192": {"coordinates": [220, 949], "shapes": ["276", "301", "308"]}, "193": {"coordinates": [231, 751], "shapes": ["277", "279", "281", "294", "295", "296"]}, "194": {"coordinates": [225, 765], "shapes": ["278", "279", "295", "299", "300"]}, "195": {"coordinates": [222, 719], "shapes": ["280", "281", "294", "298", "306", "307"]}, "196": {"coordinates": [182, 572], "shapes": ["282", "284", "303", "335", "342", "349"]}, "197": {"coordinates": [216, 655], "shapes": ["283", "285", "293", "304", "315", "316"]}, "198": {"coordinates": [215, 616], "shapes": ["287", "288", "290", "302", "317"]}, "199": {"coordinates": [209, 630], "shapes": ["289", "290", "293", "315", "317", "330"]}, "2": {"coordinates": [695, 401], "shapes": ["0", "2", "3", "11", "12"]}, "20": {"coordinates": [673, 526], "shapes": ["14", "15", "20", "27", "28", "29"]}, "200": {"coordinates": [181, 927], "shapes": ["291", "292", "301", "308", "343", "352"]}, "201": {"coordinates": [209, 732], "shapes": ["294", "296", "307", "328", "329"]}, "202": {"coordinates": [203, 753], "shapes": ["295", "296", "300", "329", "333", "334"]}, "203": {"coordinates": [212, 688], "shapes": ["297", "298", "305", "306", "320", "321"]}, "204": {"coordinates": [199, 767], "shapes": ["299", "300", "309", "333", "339"]}, "205": {"coordinates": [197, 618], "shapes": ["302", "303", "317", "330", "340", "342"]}, "206": {"coordinates": [209, 676], "shapes": ["304", "305", "316", "320", "327", "331", "332"]}, "207": {"coordinates": [200, 700], "shapes": ["306", "307", "321", "328", "337"]}, "208": {"coordinates": [177, 941], "shapes": ["308", "352", "357"]}, "209": {"coordinates": [171, 781], "shapes": ["309", "311", "339", "356", "364", "365", "366"]}, "21": {"coordinates": [666, 418], "shapes": ["16", "18", "33", "35", "36"]}, "210": {"coordinates": [154, 844], "shapes": ["310", "311", "344", "365", "373", "374"]}, "211": {"coordinates": [190, 431], "shapes": ["312", "314", "323", "338", "345", "346", "347"]}, "212": {"coordinates": [186, 445], "shapes": ["313", "314", "319", "347", "348"]}, "213": {"coordinates": [197, 636], "shapes": ["315", "316", "327", "330", "340", "341"]}, "214": {"coordinates": [182, 459], "shapes": ["318", "319", "326", "348", "350", "351"]}, "215": {"coordinates": [179, 700], "shapes": ["320", "321", "331", "337", "353", "354"]}, "216": {"coordinates": [199, 426], "shapes": ["322", "323", "324", "338"]}, "217": {"coordinates": [193, 416], "shapes": ["324", "338", "345"]}, "218": {"coordinates": [174, 487], "shapes": ["325", "326", "336", "351", "358", "359"]}, "219": {"coordinates": [173, 657], "shapes": ["327", "332", "341", "362", "363"]}, "22": {"coordinates": [659, 443], "shapes": ["17", "18", "22", "35", "37", "38"]}, "220": {"coordinates": [174, 733], "shapes": ["328", "329", "334", "337", "354", "355", "360", "361"]}, "221": {"coordinates": [173, 674], "shapes": ["331", "332", "353", "362"]}, "222": {"coordinates": [179, 752], "shapes": ["333", "334", "339", "355", "356"]}, "223": {"coordinates": [155, 558], "shapes": ["335", "336", "349", "359", "369", "371", "372"]}, "224": {"coordinates": [162, 650], "shapes": ["340", "341", "342", "349", "363", "368", "369", "370"]}, "225": {"coordinates": [135, 915], "shapes": ["343", "344", "352", "357", "373", "377", "378"]}, "226": {"coordinates": [181, 421], "shapes": ["345", "346"]}, "227": {"coordinates": [177, 435], "shapes": ["346", "347"]}, "228": {"coordinates": [173, 449], "shapes": ["348", "350"]}, "229": {"coordinates": [166, 477], "shapes": ["350", "351", "358"]}, "23": {"coordinates": [672, 279], "shapes": ["19", "31"]}, "230": {"coordinates": [163, 696], "shapes": ["353", "354", "360", "362", "363", "368"]}, "231": {"coordinates": [163, 742], "shapes": ["355", "356", "361", "364", "367"]}, "232": {"coordinates": [131, 929], "shapes": ["357", "377"]}, "233": {"coordinates": [147, 548], "shapes": ["358", "359", "371"]}, "234": {"coordinates": [149, 697], "shapes": ["360", "361", "367", "368", "370", "375", "376"]}, "235": {"coordinates": [130, 767], "shapes": ["364", "366", "367", "376", "380", "381"]}, "236": {"coordinates": [117, 817], "shapes": ["365", "366", "374", "380", "383", "384"]}, "237": {"coordinates": [129, 656], "shapes": ["369", "370", "372", "375", "379", "382"]}, "238": {"coordinates": [134, 597], "shapes": ["371", "372", "379"]}, "239": {"coordinates": [94, 901], "shapes": ["373", "374", "378", "383", "388", "389"]}, "24": {"coordinates": [658, 561], "shapes": ["20", "28", "39"]}, "240": {"coordinates": [103, 754], "shapes": ["375", "376", "381", "382", "385", "386", "387"]}, "241": {"coordinates": [91, 915], "shapes": ["377", "378", "388"]}, "242": {"coordinates": [108, 695], "shapes": ["379", "382", "385"]}, "243": {"coordinates": [92, 796], "shapes": ["380", "381", "384", "387", "390", "391"]}, "244": {"coordinates": [67, 887], "shapes": ["383", "384", "389", "391", "392", "393"]}, "245": {"coordinates": [95, 744], "shapes": ["385", "386"]}, "246": {"coordinates": [84, 783], "shapes": ["386", "387", "390"]}, "247": {"coordinates": [64, 901], "shapes": ["388", "389", "393"]}, "248": {"coordinates": [59, 877], "shapes": ["390", "391", "392"]}, "249": {"coordinates": [55, 891], "shapes": ["392", "393"]}, "25": {"coordinates": [650, 475], "shapes": ["21", "22", "34", "37", "41", "42"]}, "26": {"coordinates": [649, 370], "shapes": ["23", "24", "26", "32", "43", "44", "45"]}, "27": {"coordinates": [672, 603], "shapes": ["25", "30"]}, "28": {"coordinates": [663, 583], "shapes": ["25", "30"]}, "29": {"coordinates": [636, 352], "shapes": ["26", "43", "50", "53"]}, "3": {"coordinates": [707, 446], "shapes": ["1", "5", "8"]}, "30": {"coordinates": [644, 499], "shapes": ["27", "29", "34", "42", "46", "48"]}, "31": {"coordinates": [644, 533], "shapes": ["28", "29", "39", "46", "47"]}, "32": {"coordinates": [651, 598], "shapes": ["30"]}, "33": {"coordinates": [656, 290], "shapes": ["31", "40"]}, "34": {"coordinates": [655, 268], "shapes": ["31", "40"]}, "35": {"coordinates": [611, 407], "shapes": ["32", "33", "36", "44", "55", "67", "68"]}, "36": {"coordinates": [626, 432], "shapes": ["35", "36", "38", "51", "55", "56"]}, "37": {"coordinates": [637, 457], "shapes": ["37", "38", "41", "51", "52"]}, "38": {"coordinates": [618, 564], "shapes": ["39", "47", "58"]}, "39": {"coordinates": [639, 278], "shapes": ["40"]}, "4": {"coordinates": [691, 427], "shapes": ["1", "2", "8", "12", "16", "17", "18"]}, "40": {"coordinates": [620, 499], "shapes": ["41", "42", "48", "52", "57", "60", "61"]}, "41": {"coordinates": [617, 367], "shapes": ["43", "45", "53", "62", "63"]}, "42": {"coordinates": [610, 382], "shapes": ["44", "45", "63", "67", "69"]}, "43": {"coordinates": [621, 520], "shapes": ["46", "47", "48", "57", "58", "59"]}, "44": {"coordinates": [633, 303], "shapes": ["49", "54"]}, "45": {"coordinates": [643, 327], "shapes": ["49", "50"]}, "46": {"coordinates": [611, 346], "shapes": ["49", "50", "53", "54", "62", "64", "66"]}, "47": {"coordinates": [600, 461], "shapes": ["51", "52", "56", "60", "70", "72", "73"]}, "48": {"coordinates": [612, 289], "shapes": ["54", "64", "65"]}, "49": {"coordinates": [597, 429], "shapes": ["55", "56", "68", "72", "77"]}, "5": {"coordinates": [682, 379], "shapes": ["3", "4", "11", "23", "24"]}, "50": {"coordinates": [588, 508], "shapes": ["57", "59", "61", "71", "78", "79"]}, "51": {"coordinates": [585, 542], "shapes": ["58", "59", "78", "81", "82", "83"]}, "52": {"coordinates": [601, 491], "shapes": ["60", "61", "70", "71"]}, "53": {"coordinates": [599, 369], "shapes": ["62", "63", "66", "69", "74", "75", "76"]}, "54": {"coordinates": [579, 338], "shapes": ["64", "65", "66", "74", "80", "85", "86"]}, "55": {"coordinates": [586, 291], "shapes": ["65", "80"]}, "56": {"coordinates": [580, 411], "shapes": ["67", "68", "69", "75", "77", "84"]}, "57": {"coordinates": [557, 495], "shapes": ["70", "71", "73", "79", "88", "93", "99", "100", "101"]}, "58": {"coordinates": [554, 432], "shapes": ["72", "73", "77", "84", "97", "99", "102", "103", "104"]}, "59": {"coordinates": [569, 355], "shapes": ["74", "76", "86", "89", "90"]}, "6": {"coordinates": [675, 350], "shapes": ["4", "23", "26"]}, "60": {"coordinates": [558, 397], "shapes": ["75", "76", "84", "90", "96", "97", "98"]}, "61": {"coordinates": [576, 518], "shapes": ["78", "79", "81", "88"]}, "62": {"coordinates": [567, 307], "shapes": ["80", "85"]}, "63": {"coordinates": [558, 526], "shapes": ["81", "83", "88", "93", "94", "95"]}, "64": {"coordinates": [578, 567], "shapes": ["82", "87"]}, "65": {"coordinates": [551, 562], "shapes": ["82", "83", "87", "92", "94", "105"]}, "66": {"coordinates": [560, 332], "shapes": ["85", "86", "89", "91"]}, "67": {"coordinates": [559, 583], "shapes": ["87", "92"]}, "68": {"coordinates": [545, 364], "shapes": ["89", "90", "91", "96", "106", "107"]}, "69": {"coordinates": [503, 342], "shapes": ["91", "107", "124"]}, "7": {"coordinates": [708, 472], "shapes": ["5", "6"]}, "70": {"coordinates": [533, 584], "shapes": ["92", "105", "112"]}, "71": {"coordinates": [532, 521], "shapes": ["93", "95", "101", "114", "115"]}, "72": {"coordinates": [521, 548], "shapes": ["94", "95", "105", "112", "115", "119", "120"]}, "73": {"coordinates": [532, 386], "shapes": ["96", "98", "106", "108"]}, "74": {"coordinates": [533, 411], "shapes": ["97", "98", "104", "108", "113"]}, "75": {"coordinates": [533, 466], "shapes": ["99", "100", "102", "109", "110", "111"]}, "76": {"coordinates": [522, 508], "shapes": ["100", "101", "110", "114", "118"]}, "77": {"coordinates": [526, 441], "shapes": ["102", "103", "109", "116", "117"]}, "78": {"coordinates": [422, 397], "shapes": ["103", "104", "113", "117", "127", "131"]}, "79": {"coordinates": [461, 381], "shapes": ["106", "107", "108", "113", "124", "126", "127", "128"]}, "8": {"coordinates": [684, 461], "shapes": ["5", "6", "8", "13", "17", "21", "22"]}, "80": {"coordinates": [510, 466], "shapes": ["109", "111", "116", "121"]}, "81": {"coordinates": [512, 495], "shapes": ["110", "111", "118", "121", "122", "123"]}, "82": {"coordinates": [512, 570], "shapes": ["112", "120"]}, "83": {"coordinates": [509, 522], "shapes": ["114", "115", "118", "119", "122"]}, "84": {"coordinates": [439, 429], "shapes": ["116", "117", "121", "123", "125", "131", "132", "133"]}, "85": {"coordinates": [503, 546], "shapes": ["119", "120"]}, "86": {"coordinates": [465, 484], "shapes": ["122", "123", "125"]}, "87": {"coordinates": [446, 352], "shapes": ["124", "126"]}, "88": {"coordinates": [421, 447], "shapes": ["125", "132"]}, "89": {"coordinates": [389, 362], "shapes": ["126", "128"]}, "9": {"coordinates": [694, 493], "shapes": ["6", "13", "14", "15"]}, "90": {"coordinates": [332, 372], "shapes": ["127", "128", "131", "133", "175", "180"]}, "91": {"coordinates": [458, 592], "shapes": ["129"]}, "92": {"coordinates": [436, 604], "shapes": ["129", "130"]}, "93": {"coordinates": [444, 583], "shapes": ["129", "130"]}, "94": {"coordinates": [425, 589], "shapes": ["130", "134"]}, "95": {"coordinates": [377, 410], "shapes": ["132", "133"]}, "96": {"coordinates": [421, 574], "shapes": ["134", "135"]}, "97": {"coordinates": [406, 587], "shapes": ["134", "135"]}, "98": {"coordinates": [407, 562], "shapes": ["135"]}, "99": {"coordinates": [380, 466], "shapes": ["136", "141", "142"]}}}