{"date": "2023-05-07", "displayDate": "Sunday, May 7", "id": "1147", "palette": ["#f0e0ce", "#e97224", "#969895", "#304557", "#bd3e00", "#cbc3b8", "#10242f", "#6e5618", "#556b6f"], "puzzleConstructor": "Burgess Voshell", "shapes": [{"color": "5", "vertices": [0, 1, 2]}, {"color": "6", "vertices": [1, 2, 3]}, {"color": "6", "vertices": [2, 3, 4]}, {"color": "6", "vertices": [5, 6, 7]}, {"color": "3", "vertices": [5, 7, 8]}, {"color": "6", "vertices": [1, 3, 9]}, {"color": "8", "vertices": [1, 8, 9]}, {"color": "3", "vertices": [3, 4, 8]}, {"color": "3", "vertices": [3, 8, 9]}, {"color": "8", "vertices": [4, 10, 11]}, {"color": "8", "vertices": [4, 8, 11]}, {"color": "3", "vertices": [10, 11, 12]}, {"color": "3", "vertices": [10, 12, 13]}, {"color": "3", "vertices": [11, 12, 14]}, {"color": "8", "vertices": [8, 11, 15]}, {"color": "8", "vertices": [11, 14, 15]}, {"color": "8", "vertices": [8, 15, 16]}, {"color": "3", "vertices": [7, 8, 17]}, {"color": "3", "vertices": [8, 17, 18]}, {"color": "3", "vertices": [8, 16, 18]}, {"color": "8", "vertices": [15, 16, 19]}, {"color": "3", "vertices": [14, 15, 19]}, {"color": "3", "vertices": [14, 19, 20]}, {"color": "3", "vertices": [12, 13, 20]}, {"color": "3", "vertices": [12, 14, 20]}, {"color": "8", "vertices": [17, 18, 21]}, {"color": "8", "vertices": [16, 18, 22]}, {"color": "8", "vertices": [18, 21, 22]}, {"color": "3", "vertices": [23, 24, 25]}, {"color": "2", "vertices": [16, 22, 26]}, {"color": "2", "vertices": [16, 26, 27]}, {"color": "5", "vertices": [16, 27, 28]}, {"color": "8", "vertices": [16, 19, 28]}, {"color": "8", "vertices": [13, 20, 29]}, {"color": "8", "vertices": [13, 29, 30]}, {"color": "8", "vertices": [21, 22, 31]}, {"color": "7", "vertices": [32, 33, 34]}, {"color": "7", "vertices": [35, 36, 37]}, {"color": "4", "vertices": [35, 37, 38]}, {"color": "7", "vertices": [36, 39, 40]}, {"color": "7", "vertices": [36, 37, 40]}, {"color": "7", "vertices": [39, 41, 42]}, {"color": "7", "vertices": [39, 40, 42]}, {"color": "7", "vertices": [41, 42, 43]}, {"color": "3", "vertices": [44, 45, 46]}, {"color": "3", "vertices": [19, 20, 28]}, {"color": "4", "vertices": [47, 48, 49]}, {"color": "3", "vertices": [50, 51, 52]}, {"color": "8", "vertices": [22, 26, 31]}, {"color": "7", "isPreDrawn": true, "vertices": [37, 40, 53]}, {"color": "4", "vertices": [40, 42, 53]}, {"color": "3", "vertices": [20, 28, 29]}, {"color": "4", "vertices": [37, 38, 54]}, {"color": "4", "vertices": [37, 53, 55]}, {"color": "4", "vertices": [42, 43, 53]}, {"color": "7", "vertices": [37, 54, 55]}, {"color": "7", "vertices": [38, 54, 56]}, {"color": "4", "vertices": [53, 55, 57]}, {"color": "4", "vertices": [43, 53, 57]}, {"color": "2", "vertices": [26, 31, 58]}, {"color": "7", "vertices": [31, 58, 59]}, {"color": "4", "vertices": [58, 59, 60]}, {"color": "1", "vertices": [59, 60, 61]}, {"color": "2", "vertices": [26, 27, 62]}, {"color": "0", "vertices": [26, 58, 62]}, {"color": "1", "vertices": [54, 56, 63]}, {"color": "7", "vertices": [54, 55, 64]}, {"color": "1", "vertices": [54, 63, 64]}, {"color": "5", "vertices": [27, 28, 65]}, {"color": "2", "vertices": [27, 62, 65]}, {"color": "1", "vertices": [56, 61, 66]}, {"color": "1", "vertices": [56, 63, 66]}, {"color": "1", "vertices": [60, 61, 66]}, {"color": "8", "vertices": [29, 30, 67]}, {"color": "2", "vertices": [30, 67, 68]}, {"color": "2", "vertices": [58, 62, 69]}, {"color": "3", "vertices": [28, 29, 70]}, {"color": "4", "vertices": [43, 57, 71]}, {"color": "0", "vertices": [28, 65, 72]}, {"color": "0", "vertices": [28, 70, 72]}, {"color": "2", "vertices": [62, 69, 73]}, {"color": "2", "vertices": [62, 65, 73]}, {"color": "4", "vertices": [74, 75, 76]}, {"color": "8", "vertices": [77, 78, 79]}, {"color": "8", "isPreDrawn": true, "vertices": [29, 67, 70]}, {"color": "4", "vertices": [69, 80, 81]}, {"color": "7", "vertices": [69, 73, 81]}, {"color": "2", "vertices": [82, 83, 84]}, {"color": "5", "vertices": [83, 85, 86]}, {"color": "5", "vertices": [83, 84, 86]}, {"color": "7", "vertices": [25, 71, 87]}, {"color": "4", "vertices": [55, 57, 88]}, {"color": "7", "vertices": [55, 64, 88]}, {"color": "1", "vertices": [63, 80, 89]}, {"color": "1", "vertices": [63, 89, 90]}, {"color": "7", "vertices": [63, 64, 90]}, {"color": "1", "vertices": [80, 81, 89]}, {"color": "5", "vertices": [68, 85, 91]}, {"color": "5", "vertices": [68, 91, 92]}, {"color": "5", "vertices": [67, 68, 92]}, {"color": "5", "vertices": [85, 86, 91]}, {"color": "5", "vertices": [82, 84, 93]}, {"color": "5", "vertices": [67, 70, 94]}, {"color": "0", "vertices": [67, 92, 95]}, {"color": "0", "vertices": [67, 94, 95]}, {"color": "5", "vertices": [70, 72, 94]}, {"color": "2", "vertices": [65, 73, 96]}, {"color": "0", "vertices": [84, 86, 97]}, {"color": "0", "vertices": [84, 97, 98]}, {"color": "0", "vertices": [84, 93, 98]}, {"color": "3", "vertices": [34, 99, 100]}, {"color": "0", "vertices": [86, 91, 101]}, {"color": "5", "vertices": [86, 101, 102]}, {"color": "0", "vertices": [86, 97, 102]}, {"color": "0", "vertices": [65, 72, 103]}, {"color": "5", "vertices": [65, 96, 103]}, {"color": "0", "vertices": [91, 101, 104]}, {"color": "0", "vertices": [91, 92, 105]}, {"color": "0", "vertices": [91, 104, 105]}, {"color": "0", "vertices": [92, 95, 106]}, {"color": "0", "vertices": [92, 105, 106]}, {"color": "2", "vertices": [101, 102, 104]}, {"color": "7", "vertices": [64, 88, 90]}, {"color": "0", "vertices": [72, 94, 103]}, {"color": "6", "vertices": [48, 107, 108]}, {"color": "6", "vertices": [97, 98, 109]}, {"color": "5", "vertices": [97, 102, 109]}, {"color": "0", "vertices": [93, 98, 110]}, {"color": "7", "vertices": [57, 88, 111]}, {"color": "7", "vertices": [57, 71, 111]}, {"color": "5", "vertices": [102, 109, 112]}, {"color": "0", "vertices": [98, 109, 110]}, {"color": "2", "vertices": [102, 104, 112]}, {"color": "7", "vertices": [88, 90, 113]}, {"color": "4", "vertices": [71, 111, 114]}, {"color": "5", "vertices": [96, 103, 115]}, {"color": "4", "vertices": [88, 111, 116]}, {"color": "1", "vertices": [88, 113, 116]}, {"color": "0", "vertices": [109, 110, 117]}, {"color": "5", "vertices": [109, 112, 117]}, {"color": "0", "vertices": [94, 95, 103]}, {"color": "5", "vertices": [95, 103, 115]}, {"color": "1", "vertices": [111, 114, 116]}, {"color": "0", "vertices": [110, 117, 118]}, {"color": "4", "vertices": [112, 117, 119]}, {"color": "4", "vertices": [117, 119, 120]}, {"color": "1", "vertices": [117, 118, 120]}, {"color": "5", "vertices": [95, 106, 121]}, {"color": "0", "vertices": [95, 115, 121]}, {"color": "4", "vertices": [119, 120, 122]}], "theme": "Appear on a pier", "vertices": {"0": {"coordinates": [646, 553], "shapes": ["0"]}, "1": {"coordinates": [580, 544], "shapes": ["0", "1", "5", "6"]}, "10": {"coordinates": [534, 475], "shapes": ["9", "11", "12"]}, "100": {"coordinates": [295, 1043], "shapes": ["110"]}, "101": {"coordinates": [354, 315], "shapes": ["111", "112", "116", "121"]}, "102": {"coordinates": [336, 310], "shapes": ["112", "113", "121", "126", "130", "132"]}, "103": {"coordinates": [321, 494], "shapes": ["114", "115", "123", "135", "140", "141"]}, "104": {"coordinates": [316, 320], "shapes": ["116", "118", "121", "132"]}, "105": {"coordinates": [302, 356], "shapes": ["117", "118", "120"]}, "106": {"coordinates": [291, 390], "shapes": ["119", "120", "147"]}, "107": {"coordinates": [307, 1021], "shapes": ["124"]}, "108": {"coordinates": [270, 1009], "shapes": ["124"]}, "109": {"coordinates": [322, 282], "shapes": ["125", "126", "130", "131", "138", "139"]}, "11": {"coordinates": [525, 504], "shapes": ["9", "10", "11", "13", "14", "15"]}, "110": {"coordinates": [315, 262], "shapes": ["127", "131", "138", "143"]}, "111": {"coordinates": [325, 746], "shapes": ["128", "129", "134", "136", "142"]}, "112": {"coordinates": [302, 302], "shapes": ["130", "132", "139", "144"]}, "113": {"coordinates": [292, 628], "shapes": ["133", "137"]}, "114": {"coordinates": [292, 936], "shapes": ["134", "142"]}, "115": {"coordinates": [290, 475], "shapes": ["135", "141", "148"]}, "116": {"coordinates": [292, 685], "shapes": ["136", "137", "142"]}, "117": {"coordinates": [308, 288], "shapes": ["138", "139", "143", "144", "145", "146"]}, "118": {"coordinates": [292, 285], "shapes": ["143", "146"]}, "119": {"coordinates": [281, 306], "shapes": ["144", "145", "149"]}, "12": {"coordinates": [499, 473], "shapes": ["11", "12", "13", "23", "24"]}, "120": {"coordinates": [262, 294], "shapes": ["145", "146", "149"]}, "121": {"coordinates": [283, 432], "shapes": ["147", "148"]}, "122": {"coordinates": [252, 317], "shapes": ["149"]}, "13": {"coordinates": [471, 419], "shapes": ["12", "23", "33", "34"]}, "14": {"coordinates": [473, 476], "shapes": ["13", "15", "21", "22", "24"]}, "15": {"coordinates": [502, 501], "shapes": ["14", "15", "16", "20", "21"]}, "16": {"coordinates": [474, 514], "shapes": ["16", "19", "20", "26", "29", "30", "31", "32"]}, "17": {"coordinates": [499, 543], "shapes": ["17", "18", "25"]}, "18": {"coordinates": [481, 532], "shapes": ["18", "19", "25", "26", "27"]}, "19": {"coordinates": [450, 492], "shapes": ["20", "21", "22", "32", "45"]}, "2": {"coordinates": [616, 537], "shapes": ["0", "1", "2"]}, "20": {"coordinates": [440, 450], "shapes": ["22", "23", "24", "33", "45", "51"]}, "21": {"coordinates": [468, 553], "shapes": ["25", "27", "35"]}, "22": {"coordinates": [443, 537], "shapes": ["26", "27", "29", "35", "48"]}, "23": {"coordinates": [481, 968], "shapes": ["28"]}, "24": {"coordinates": [441, 974], "shapes": ["28"]}, "25": {"coordinates": [394, 968], "shapes": ["28", "90"]}, "26": {"coordinates": [419, 532], "shapes": ["29", "30", "48", "59", "63", "64"]}, "27": {"coordinates": [413, 518], "shapes": ["30", "31", "63", "68", "69"]}, "28": {"coordinates": [405, 478], "shapes": ["31", "32", "45", "51", "68", "76", "78", "79"]}, "29": {"coordinates": [395, 434], "shapes": ["33", "34", "51", "73", "76", "84"]}, "3": {"coordinates": [568, 514], "shapes": ["1", "2", "5", "7", "8"]}, "30": {"coordinates": [407, 386], "shapes": ["34", "73", "74"]}, "31": {"coordinates": [423, 557], "shapes": ["35", "48", "59", "60"]}, "32": {"coordinates": [468, 1056], "shapes": ["36"]}, "33": {"coordinates": [397, 1069], "shapes": ["36"]}, "34": {"coordinates": [332, 1056], "shapes": ["36", "110"]}, "35": {"coordinates": [467, 627], "shapes": ["37", "38"]}, "36": {"coordinates": [466, 689], "shapes": ["37", "39", "40"]}, "37": {"coordinates": [438, 642], "shapes": ["37", "38", "40", "49", "52", "53", "55"]}, "38": {"coordinates": [438, 619], "shapes": ["38", "52", "56"]}, "39": {"coordinates": [465, 813], "shapes": ["39", "41", "42"]}, "4": {"coordinates": [556, 499], "shapes": ["2", "7", "9", "10"]}, "40": {"coordinates": [445, 740], "shapes": ["39", "40", "42", "49", "50"]}, "41": {"coordinates": [465, 946], "shapes": ["41", "43"]}, "42": {"coordinates": [438, 880], "shapes": ["41", "42", "43", "50", "54"]}, "43": {"coordinates": [409, 935], "shapes": ["43", "54", "58", "77"]}, "44": {"coordinates": [459, 1135], "shapes": ["44"]}, "45": {"coordinates": [413, 1146], "shapes": ["44"]}, "46": {"coordinates": [376, 1135], "shapes": ["44"]}, "47": {"coordinates": [454, 1009], "shapes": ["46"]}, "48": {"coordinates": [353, 1009], "shapes": ["46", "124"]}, "49": {"coordinates": [406, 995], "shapes": ["46"]}, "5": {"coordinates": [593, 555], "shapes": ["3", "4"]}, "50": {"coordinates": [451, 988], "shapes": ["47"]}, "51": {"coordinates": [283, 986], "shapes": ["47"]}, "52": {"coordinates": [367, 974], "shapes": ["47"]}, "53": {"coordinates": [429, 805], "shapes": ["49", "50", "53", "54", "57", "58"]}, "54": {"coordinates": [418, 635], "shapes": ["52", "55", "56", "65", "66", "67"]}, "55": {"coordinates": [392, 646], "shapes": ["53", "55", "57", "66", "91", "92"]}, "56": {"coordinates": [418, 619], "shapes": ["56", "65", "70", "71"]}, "57": {"coordinates": [342, 852], "shapes": ["57", "58", "77", "91", "128", "129"]}, "58": {"coordinates": [406, 556], "shapes": ["59", "60", "61", "64", "75"]}, "59": {"coordinates": [420, 573], "shapes": ["60", "61", "62"]}, "6": {"coordinates": [561, 563], "shapes": ["3"]}, "60": {"coordinates": [405, 576], "shapes": ["61", "62", "72"]}, "61": {"coordinates": [417, 591], "shapes": ["62", "70", "72"]}, "62": {"coordinates": [400, 537], "shapes": ["63", "64", "69", "75", "80", "81"]}, "63": {"coordinates": [390, 627], "shapes": ["65", "67", "71", "93", "94", "95"]}, "64": {"coordinates": [357, 635], "shapes": ["66", "67", "92", "95", "122"]}, "65": {"coordinates": [359, 512], "shapes": ["68", "69", "78", "81", "106", "114", "115"]}, "66": {"coordinates": [406, 610], "shapes": ["70", "71", "72"]}, "67": {"coordinates": [376, 405], "shapes": ["73", "74", "84", "99", "102", "103", "104"]}, "68": {"coordinates": [381, 367], "shapes": ["74", "97", "98", "99"]}, "69": {"coordinates": [390, 553], "shapes": ["75", "80", "85", "86"]}, "7": {"coordinates": [522, 553], "shapes": ["3", "4", "17"]}, "70": {"coordinates": [376, 451], "shapes": ["76", "79", "84", "102", "105"]}, "71": {"coordinates": [332, 946], "shapes": ["77", "90", "129", "134"]}, "72": {"coordinates": [350, 473], "shapes": ["78", "79", "105", "114", "123"]}, "73": {"coordinates": [374, 548], "shapes": ["80", "81", "86", "106"]}, "74": {"coordinates": [404, 1107], "shapes": ["82"]}, "75": {"coordinates": [303, 1107], "shapes": ["82"]}, "76": {"coordinates": [356, 1092], "shapes": ["82"]}, "77": {"coordinates": [404, 1185], "shapes": ["83"]}, "78": {"coordinates": [364, 1191], "shapes": ["83"]}, "79": {"coordinates": [317, 1185], "shapes": ["83"]}, "8": {"coordinates": [522, 523], "shapes": ["4", "6", "7", "8", "10", "14", "16", "17", "18", "19"]}, "80": {"coordinates": [392, 587], "shapes": ["85", "93", "96"]}, "81": {"coordinates": [377, 574], "shapes": ["85", "86", "96"]}, "82": {"coordinates": [377, 262], "shapes": ["87", "101"]}, "83": {"coordinates": [389, 293], "shapes": ["87", "88", "89"]}, "84": {"coordinates": [372, 279], "shapes": ["87", "89", "101", "107", "108", "109"]}, "85": {"coordinates": [380, 343], "shapes": ["88", "97", "100"]}, "86": {"coordinates": [369, 304], "shapes": ["88", "89", "100", "107", "111", "112", "113"]}, "87": {"coordinates": [273, 968], "shapes": ["90"]}, "88": {"coordinates": [329, 643], "shapes": ["91", "92", "122", "128", "133", "136", "137"]}, "89": {"coordinates": [380, 613], "shapes": ["93", "94", "96"]}, "9": {"coordinates": [559, 531], "shapes": ["5", "6", "8"]}, "90": {"coordinates": [332, 628], "shapes": ["94", "95", "122", "133"]}, "91": {"coordinates": [359, 338], "shapes": ["97", "98", "100", "111", "116", "117", "118"]}, "92": {"coordinates": [356, 379], "shapes": ["98", "99", "103", "117", "119", "120"]}, "93": {"coordinates": [346, 253], "shapes": ["101", "109", "127"]}, "94": {"coordinates": [312, 470], "shapes": ["102", "104", "105", "123", "140"]}, "95": {"coordinates": [292, 456], "shapes": ["103", "104", "119", "140", "141", "147", "148"]}, "96": {"coordinates": [327, 523], "shapes": ["106", "115", "135"]}, "97": {"coordinates": [346, 282], "shapes": ["107", "108", "113", "125", "126"]}, "98": {"coordinates": [336, 270], "shapes": ["108", "109", "125", "127", "131"]}, "99": {"coordinates": [374, 1043], "shapes": ["110"]}}}