{"date": "2022-10-12", "displayDate": "Wednesday, October 12", "id": "941", "palette": ["#E8DF87", "#EBCF16", "#65677D", "#C49B0B", "#E0CCA7", "#130D16", "#281C16", "#3A2D32", "#514141"], "puzzleConstructor": "Burgess Voshell", "shapes": [{"color": "7", "vertices": [0, 1, 2]}, {"color": "7", "vertices": [1, 2, 3]}, {"color": "6", "isPreDrawn": true, "vertices": [4, 5, 6]}, {"color": "7", "vertices": [5, 7, 8]}, {"color": "3", "vertices": [9, 10, 11]}, {"color": "0", "vertices": [10, 11, 12]}, {"color": "4", "vertices": [13, 14, 15]}, {"color": "4", "vertices": [14, 15, 16]}, {"color": "1", "vertices": [10, 12, 17]}, {"color": "4", "vertices": [15, 16, 18]}, {"color": "4", "vertices": [16, 18, 19]}, {"color": "1", "vertices": [20, 21, 22]}, {"color": "7", "vertices": [20, 22, 23]}, {"color": "0", "vertices": [23, 24, 25]}, {"color": "8", "vertices": [22, 23, 26]}, {"color": "3", "vertices": [21, 22, 27]}, {"color": "1", "vertices": [23, 25, 26]}, {"color": "7", "vertices": [24, 25, 28]}, {"color": "1", "vertices": [12, 17, 29]}, {"color": "0", "vertices": [28, 30, 31]}, {"color": "8", "vertices": [25, 28, 32]}, {"color": "1", "vertices": [28, 31, 32]}, {"color": "7", "vertices": [22, 26, 33]}, {"color": "6", "vertices": [22, 27, 33]}, {"color": "7", "vertices": [30, 31, 34]}, {"color": "1", "vertices": [25, 26, 35]}, {"color": "7", "vertices": [25, 35, 36]}, {"color": "7", "vertices": [25, 32, 36]}, {"color": "3", "vertices": [26, 33, 35]}, {"color": "0", "vertices": [34, 37, 38]}, {"color": "8", "vertices": [31, 34, 39]}, {"color": "1", "vertices": [34, 38, 39]}, {"color": "1", "vertices": [17, 29, 40]}, {"color": "1", "vertices": [31, 32, 41]}, {"color": "7", "vertices": [31, 39, 41]}, {"color": "3", "vertices": [29, 40, 42]}, {"color": "0", "vertices": [29, 42, 43]}, {"color": "3", "vertices": [33, 35, 44]}, {"color": "1", "vertices": [32, 36, 41]}, {"color": "8", "vertices": [37, 38, 45]}, {"color": "6", "vertices": [35, 36, 46]}, {"color": "7", "vertices": [35, 44, 46]}, {"color": "3", "vertices": [36, 41, 46]}, {"color": "1", "vertices": [42, 43, 47]}, {"color": "7", "vertices": [39, 41, 48]}, {"color": "3", "vertices": [41, 46, 49]}, {"color": "6", "vertices": [41, 48, 49]}, {"color": "1", "vertices": [38, 39, 50]}, {"color": "1", "vertices": [39, 48, 50]}, {"color": "2", "vertices": [38, 45, 51]}, {"color": "7", "vertices": [38, 50, 51]}, {"color": "1", "vertices": [45, 51, 52]}, {"color": "3", "vertices": [48, 50, 53]}, {"color": "7", "vertices": [48, 49, 54]}, {"color": "0", "vertices": [45, 52, 55]}, {"color": "3", "vertices": [48, 53, 54]}, {"color": "6", "vertices": [50, 51, 56]}, {"color": "7", "vertices": [50, 53, 56]}, {"color": "3", "vertices": [43, 47, 57]}, {"color": "4", "vertices": [18, 19, 58]}, {"color": "0", "vertices": [19, 58, 59]}, {"color": "7", "vertices": [52, 55, 60]}, {"color": "3", "vertices": [47, 57, 61]}, {"color": "1", "vertices": [51, 52, 62]}, {"color": "3", "vertices": [51, 56, 62]}, {"color": "3", "vertices": [57, 61, 63]}, {"color": "7", "isPreDrawn": true, "vertices": [57, 63, 64]}, {"color": "1", "vertices": [52, 60, 65]}, {"color": "7", "vertices": [52, 62, 65]}, {"color": "5", "vertices": [60, 65, 66]}, {"color": "3", "vertices": [56, 62, 67]}, {"color": "7", "vertices": [62, 67, 68]}, {"color": "6", "vertices": [62, 65, 68]}, {"color": "4", "vertices": [69, 70, 71]}, {"color": "4", "vertices": [69, 71, 72]}, {"color": "5", "vertices": [65, 68, 73]}, {"color": "1", "vertices": [65, 66, 74]}, {"color": "6", "vertices": [65, 73, 75]}, {"color": "7", "vertices": [65, 74, 75]}, {"color": "4", "vertices": [70, 71, 76]}, {"color": "4", "vertices": [70, 76, 77]}, {"color": "6", "vertices": [63, 64, 78]}, {"color": "5", "vertices": [73, 75, 79]}, {"color": "0", "vertices": [0, 58, 59]}, {"color": "1", "vertices": [80, 81, 82]}, {"color": "3", "vertices": [81, 82, 83]}, {"color": "3", "vertices": [84, 85, 86]}, {"color": "1", "vertices": [84, 86, 87]}, {"color": "1", "vertices": [83, 87, 88]}, {"color": "1", "vertices": [82, 83, 88]}, {"color": "5", "vertices": [64, 89, 90]}, {"color": "5", "vertices": [64, 78, 91]}, {"color": "5", "vertices": [64, 90, 91]}, {"color": "0", "vertices": [86, 87, 88]}, {"color": "6", "vertices": [75, 79, 92]}, {"color": "3", "vertices": [78, 80, 93]}, {"color": "3", "vertices": [80, 82, 93]}, {"color": "5", "vertices": [89, 90, 92]}, {"color": "6", "vertices": [78, 93, 94]}, {"color": "7", "vertices": [78, 91, 94]}, {"color": "3", "vertices": [75, 92, 95]}, {"color": "0", "vertices": [0, 59, 96]}, {"color": "6", "vertices": [90, 92, 95]}, {"color": "8", "vertices": [91, 94, 97]}, {"color": "6", "vertices": [95, 98, 99]}, {"color": "5", "vertices": [90, 95, 99]}, {"color": "2", "vertices": [90, 91, 97]}, {"color": "0", "vertices": [76, 77, 100]}, {"color": "0", "vertices": [77, 100, 101]}, {"color": "5", "vertices": [90, 99, 102]}, {"color": "6", "vertices": [96, 98, 99]}, {"color": "3", "vertices": [4, 99, 102]}, {"color": "5", "vertices": [4, 96, 99]}, {"color": "3", "vertices": [4, 102, 103]}, {"color": "3", "vertices": [102, 103, 104]}, {"color": "5", "vertices": [4, 96, 105]}, {"color": "3", "vertices": [0, 96, 105]}, {"color": "3", "vertices": [106, 107, 108]}, {"color": "1", "vertices": [103, 104, 109]}, {"color": "3", "vertices": [104, 109, 110]}, {"color": "1", "vertices": [106, 110, 111]}, {"color": "1", "vertices": [106, 108, 111]}, {"color": "1", "vertices": [107, 108, 112]}, {"color": "3", "vertices": [107, 112, 113]}, {"color": "1", "vertices": [109, 110, 111]}, {"color": "3", "vertices": [0, 1, 105]}, {"color": "8", "vertices": [0, 2, 101]}, {"color": "5", "vertices": [4, 5, 103]}, {"color": "8", "vertices": [5, 103, 114]}, {"color": "6", "vertices": [4, 6, 105]}, {"color": "3", "vertices": [100, 101, 115]}, {"color": "6", "vertices": [1, 6, 105]}, {"color": "3", "vertices": [7, 114, 116]}, {"color": "8", "vertices": [5, 7, 114]}, {"color": "7", "vertices": [2, 101, 115]}, {"color": "6", "vertices": [2, 3, 115]}, {"color": "6", "vertices": [1, 3, 6]}, {"color": "0", "vertices": [116, 117, 118]}, {"color": "0", "vertices": [116, 118, 119]}, {"color": "1", "vertices": [116, 119, 120]}, {"color": "3", "vertices": [7, 116, 120]}, {"color": "7", "vertices": [3, 115, 121]}, {"color": "6", "vertices": [3, 6, 122]}, {"color": "6", "vertices": [3, 121, 122]}, {"color": "3", "vertices": [118, 119, 123]}, {"color": "3", "vertices": [119, 123, 124]}, {"color": "1", "vertices": [123, 124, 125]}, {"color": "5", "vertices": [5, 6, 8]}, {"color": "3", "vertices": [124, 125, 126]}, {"color": "1", "vertices": [125, 126, 127]}, {"color": "1", "vertices": [126, 127, 128]}, {"color": "1", "vertices": [127, 128, 129]}, {"color": "8", "vertices": [115, 121, 130]}, {"color": "3", "vertices": [128, 129, 131]}, {"color": "1", "vertices": [119, 120, 132]}, {"color": "5", "vertices": [7, 8, 133]}, {"color": "1", "vertices": [7, 120, 133]}, {"color": "1", "vertices": [6, 122, 134]}, {"color": "3", "vertices": [6, 8, 134]}, {"color": "5", "vertices": [8, 133, 134]}, {"color": "2", "vertices": [121, 130, 135]}, {"color": "5", "vertices": [121, 122, 135]}, {"color": "1", "vertices": [133, 134, 136]}, {"color": "3", "vertices": [120, 133, 136]}, {"color": "3", "vertices": [122, 134, 136]}, {"color": "5", "vertices": [122, 135, 136]}, {"color": "1", "vertices": [120, 132, 137]}, {"color": "5", "vertices": [135, 136, 138]}, {"color": "5", "vertices": [120, 136, 138]}, {"color": "3", "vertices": [120, 138, 139]}, {"color": "3", "vertices": [120, 137, 139]}, {"color": "7", "vertices": [135, 138, 140]}, {"color": "8", "vertices": [138, 139, 140]}, {"color": "7", "vertices": [135, 140, 141]}, {"color": "8", "vertices": [135, 141, 142]}, {"color": "7", "vertices": [139, 140, 143]}, {"color": "7", "vertices": [139, 143, 144]}, {"color": "8", "vertices": [141, 142, 145]}, {"color": "5", "vertices": [140, 141, 146]}, {"color": "2", "vertices": [141, 145, 146]}, {"color": "5", "vertices": [140, 143, 146]}, {"color": "7", "vertices": [142, 145, 147]}, {"color": "5", "vertices": [145, 146, 148]}, {"color": "5", "vertices": [143, 146, 148]}, {"color": "7", "vertices": [145, 148, 149]}, {"color": "8", "vertices": [145, 147, 149]}, {"color": "6", "vertices": [143, 144, 150]}, {"color": "7", "vertices": [143, 148, 151]}, {"color": "5", "vertices": [143, 150, 152]}, {"color": "7", "vertices": [143, 151, 152]}, {"color": "3", "vertices": [147, 149, 153]}, {"color": "8", "vertices": [148, 149, 151]}, {"color": "3", "vertices": [149, 153, 154]}, {"color": "1", "vertices": [153, 154, 155]}, {"color": "0", "vertices": [154, 155, 156]}, {"color": "1", "vertices": [155, 156, 157]}], "theme": "Pest with a nest", "vertices": {"0": {"coordinates": [336, 440], "shapes": ["0", "83", "101", "116", "125", "126"]}, "1": {"coordinates": [309, 455], "shapes": ["0", "1", "125", "131", "136"]}, "10": {"coordinates": [664, 841], "shapes": ["4", "5", "8"]}, "100": {"coordinates": [324, 371], "shapes": ["107", "108", "130"]}, "101": {"coordinates": [315, 429], "shapes": ["108", "126", "130", "134"]}, "102": {"coordinates": [353, 549], "shapes": ["109", "111", "113", "114"]}, "103": {"coordinates": [334, 557], "shapes": ["113", "114", "118", "127", "128"]}, "104": {"coordinates": [351, 581], "shapes": ["114", "118", "119"]}, "105": {"coordinates": [320, 466], "shapes": ["115", "116", "125", "129", "131"]}, "106": {"coordinates": [351, 658], "shapes": ["117", "120", "121"]}, "107": {"coordinates": [351, 701], "shapes": ["117", "122", "123"]}, "108": {"coordinates": [336, 653], "shapes": ["117", "121", "122"]}, "109": {"coordinates": [333, 587], "shapes": ["118", "119", "124"]}, "11": {"coordinates": [685, 842], "shapes": ["4", "5"]}, "110": {"coordinates": [347, 598], "shapes": ["119", "120", "124"]}, "111": {"coordinates": [339, 616], "shapes": ["120", "121", "124"]}, "112": {"coordinates": [336, 708], "shapes": ["122", "123"]}, "113": {"coordinates": [344, 724], "shapes": ["123"]}, "114": {"coordinates": [316, 563], "shapes": ["128", "132", "133"]}, "115": {"coordinates": [285, 425], "shapes": ["130", "134", "135", "141", "152"]}, "116": {"coordinates": [302, 570], "shapes": ["132", "137", "138", "139", "140"]}, "117": {"coordinates": [305, 583], "shapes": ["137"]}, "118": {"coordinates": [290, 579], "shapes": ["137", "138", "144"]}, "119": {"coordinates": [276, 574], "shapes": ["138", "139", "144", "145", "154"]}, "12": {"coordinates": [636, 791], "shapes": ["5", "8", "18"]}, "120": {"coordinates": [224, 543], "shapes": ["139", "140", "154", "156", "163", "166", "168", "169", "170"]}, "121": {"coordinates": [247, 448], "shapes": ["141", "143", "152", "160", "161"]}, "122": {"coordinates": [241, 473], "shapes": ["142", "143", "157", "161", "164", "165"]}, "123": {"coordinates": [293, 607], "shapes": ["144", "145", "146"]}, "124": {"coordinates": [276, 613], "shapes": ["145", "146", "148"]}, "125": {"coordinates": [287, 625], "shapes": ["146", "148", "149"]}, "126": {"coordinates": [279, 641], "shapes": ["148", "149", "150"]}, "127": {"coordinates": [285, 673], "shapes": ["149", "150", "151"]}, "128": {"coordinates": [273, 697], "shapes": ["150", "151", "153"]}, "129": {"coordinates": [276, 717], "shapes": ["151", "153"]}, "13": {"coordinates": [661, 304], "shapes": ["6"]}, "130": {"coordinates": [250, 434], "shapes": ["152", "160"]}, "131": {"coordinates": [251, 744], "shapes": ["153"]}, "132": {"coordinates": [231, 557], "shapes": ["154", "166"]}, "133": {"coordinates": [244, 541], "shapes": ["155", "156", "159", "162", "163"]}, "134": {"coordinates": [240, 490], "shapes": ["157", "158", "159", "162", "164"]}, "135": {"coordinates": [219, 458], "shapes": ["160", "161", "165", "167", "171", "173", "174"]}, "136": {"coordinates": [228, 485], "shapes": ["162", "163", "164", "165", "167", "168"]}, "137": {"coordinates": [208, 548], "shapes": ["166", "170"]}, "138": {"coordinates": [220, 504], "shapes": ["167", "168", "169", "171", "172"]}, "139": {"coordinates": [208, 522], "shapes": ["169", "170", "172", "175", "176"]}, "14": {"coordinates": [681, 326], "shapes": ["6", "7"]}, "140": {"coordinates": [198, 493], "shapes": ["171", "172", "173", "175", "178", "180"]}, "141": {"coordinates": [201, 461], "shapes": ["173", "174", "177", "178", "179"]}, "142": {"coordinates": [194, 445], "shapes": ["174", "177", "181"]}, "143": {"coordinates": [165, 531], "shapes": ["175", "176", "180", "183", "186", "187", "188", "189"]}, "144": {"coordinates": [180, 551], "shapes": ["176", "186"]}, "145": {"coordinates": [181, 461], "shapes": ["177", "179", "181", "182", "184", "185"]}, "146": {"coordinates": [185, 480], "shapes": ["178", "179", "180", "182", "183"]}, "147": {"coordinates": [159, 460], "shapes": ["181", "185", "190"]}, "148": {"coordinates": [159, 499], "shapes": ["182", "183", "184", "187", "191"]}, "149": {"coordinates": [156, 474], "shapes": ["184", "185", "190", "191", "192"]}, "15": {"coordinates": [610, 300], "shapes": ["6", "7", "9"]}, "150": {"coordinates": [157, 574], "shapes": ["186", "188"]}, "151": {"coordinates": [143, 529], "shapes": ["187", "189", "191"]}, "152": {"coordinates": [150, 550], "shapes": ["188", "189"]}, "153": {"coordinates": [130, 433], "shapes": ["190", "192", "193"]}, "154": {"coordinates": [101, 433], "shapes": ["192", "193", "194"]}, "155": {"coordinates": [83, 406], "shapes": ["193", "194", "195"]}, "156": {"coordinates": [67, 421], "shapes": ["194", "195"]}, "157": {"coordinates": [57, 409], "shapes": ["195"]}, "16": {"coordinates": [649, 344], "shapes": ["7", "9", "10"]}, "17": {"coordinates": [608, 765], "shapes": ["8", "18", "32"]}, "18": {"coordinates": [540, 321], "shapes": ["9", "10", "59"]}, "19": {"coordinates": [535, 382], "shapes": ["10", "59", "60"]}, "2": {"coordinates": [314, 441], "shapes": ["0", "1", "126", "134", "135"]}, "20": {"coordinates": [647, 669], "shapes": ["11", "12"]}, "21": {"coordinates": [647, 708], "shapes": ["11", "15"]}, "22": {"coordinates": [631, 660], "shapes": ["11", "12", "14", "15", "22", "23"]}, "23": {"coordinates": [647, 631], "shapes": ["12", "13", "14", "16"]}, "24": {"coordinates": [643, 616], "shapes": ["13", "17"]}, "25": {"coordinates": [626, 620], "shapes": ["13", "16", "17", "20", "25", "26", "27"]}, "26": {"coordinates": [616, 637], "shapes": ["14", "16", "22", "25", "28"]}, "27": {"coordinates": [621, 682], "shapes": ["15", "23"]}, "28": {"coordinates": [635, 587], "shapes": ["17", "19", "20", "21"]}, "29": {"coordinates": [600, 714], "shapes": ["18", "32", "35", "36"]}, "3": {"coordinates": [293, 448], "shapes": ["1", "135", "136", "141", "142", "143"]}, "30": {"coordinates": [626, 574], "shapes": ["19", "24"]}, "31": {"coordinates": [602, 583], "shapes": ["19", "21", "24", "30", "33", "34"]}, "32": {"coordinates": [597, 603], "shapes": ["20", "21", "27", "33", "38"]}, "33": {"coordinates": [598, 665], "shapes": ["22", "23", "28", "37"]}, "34": {"coordinates": [610, 548], "shapes": ["24", "29", "30", "31"]}, "35": {"coordinates": [595, 643], "shapes": ["25", "26", "28", "37", "40", "41"]}, "36": {"coordinates": [587, 628], "shapes": ["26", "27", "38", "40", "42"]}, "37": {"coordinates": [597, 530], "shapes": ["29", "39"]}, "38": {"coordinates": [561, 550], "shapes": ["29", "31", "39", "47", "49", "50"]}, "39": {"coordinates": [570, 572], "shapes": ["30", "31", "34", "44", "47", "48"]}, "4": {"coordinates": [331, 487], "shapes": ["2", "111", "112", "113", "115", "127", "129"]}, "40": {"coordinates": [600, 741], "shapes": ["32", "35"]}, "41": {"coordinates": [577, 611], "shapes": ["33", "34", "38", "42", "44", "45", "46"]}, "42": {"coordinates": [583, 732], "shapes": ["35", "36", "43"]}, "43": {"coordinates": [543, 649], "shapes": ["36", "43", "58"]}, "44": {"coordinates": [582, 655], "shapes": ["37", "41"]}, "45": {"coordinates": [554, 493], "shapes": ["39", "49", "51", "54"]}, "46": {"coordinates": [565, 638], "shapes": ["40", "41", "42", "45"]}, "47": {"coordinates": [525, 652], "shapes": ["43", "58", "62"]}, "48": {"coordinates": [554, 598], "shapes": ["44", "46", "48", "52", "53", "55"]}, "49": {"coordinates": [552, 625], "shapes": ["45", "46", "53"]}, "5": {"coordinates": [291, 544], "shapes": ["2", "3", "127", "128", "133", "147"]}, "50": {"coordinates": [545, 579], "shapes": ["47", "48", "50", "52", "56", "57"]}, "51": {"coordinates": [521, 538], "shapes": ["49", "50", "51", "56", "63", "64"]}, "52": {"coordinates": [510, 516], "shapes": ["51", "54", "61", "63", "67", "68"]}, "53": {"coordinates": [522, 598], "shapes": ["52", "55", "57"]}, "54": {"coordinates": [535, 609], "shapes": ["53", "55"]}, "55": {"coordinates": [535, 485], "shapes": ["54", "61"]}, "56": {"coordinates": [504, 583], "shapes": ["56", "57", "64", "70"]}, "57": {"coordinates": [520, 637], "shapes": ["58", "62", "65", "66"]}, "58": {"coordinates": [436, 382], "shapes": ["59", "60", "83"]}, "59": {"coordinates": [407, 437], "shapes": ["60", "83", "101"]}, "6": {"coordinates": [260, 493], "shapes": ["2", "129", "131", "136", "142", "147", "157", "158"]}, "60": {"coordinates": [504, 472], "shapes": ["61", "67", "69"]}, "61": {"coordinates": [507, 649], "shapes": ["62", "65"]}, "62": {"coordinates": [501, 551], "shapes": ["63", "64", "68", "70", "71", "72"]}, "63": {"coordinates": [446, 621], "shapes": ["65", "66", "81"]}, "64": {"coordinates": [427, 579], "shapes": ["66", "81", "90", "91", "92"]}, "65": {"coordinates": [460, 517], "shapes": ["67", "68", "69", "72", "75", "76", "77", "78"]}, "66": {"coordinates": [457, 470], "shapes": ["69", "76"]}, "67": {"coordinates": [487, 577], "shapes": ["70", "71"]}, "68": {"coordinates": [462, 561], "shapes": ["71", "72", "75"]}, "69": {"coordinates": [476, 253], "shapes": ["73", "74"]}, "7": {"coordinates": [269, 548], "shapes": ["3", "132", "133", "140", "155", "156"]}, "70": {"coordinates": [450, 289], "shapes": ["73", "79", "80"]}, "71": {"coordinates": [426, 261], "shapes": ["73", "74", "79"]}, "72": {"coordinates": [462, 244], "shapes": ["74"]}, "73": {"coordinates": [446, 529], "shapes": ["75", "77", "82"]}, "74": {"coordinates": [409, 498], "shapes": ["76", "78"]}, "75": {"coordinates": [409, 515], "shapes": ["77", "78", "82", "94", "100"]}, "76": {"coordinates": [373, 314], "shapes": ["79", "80", "107"]}, "77": {"coordinates": [377, 356], "shapes": ["80", "107", "108"]}, "78": {"coordinates": [415, 589], "shapes": ["81", "91", "95", "98", "99"]}, "79": {"coordinates": [424, 539], "shapes": ["82", "94"]}, "8": {"coordinates": [254, 526], "shapes": ["3", "147", "155", "158", "159"]}, "80": {"coordinates": [422, 622], "shapes": ["84", "95", "96"]}, "81": {"coordinates": [436, 701], "shapes": ["84", "85"]}, "82": {"coordinates": [412, 708], "shapes": ["84", "85", "89", "96"]}, "83": {"coordinates": [428, 718], "shapes": ["85", "88", "89"]}, "84": {"coordinates": [430, 845], "shapes": ["86", "87"]}, "85": {"coordinates": [430, 891], "shapes": ["86"]}, "86": {"coordinates": [413, 807], "shapes": ["86", "87", "93"]}, "87": {"coordinates": [424, 769], "shapes": ["87", "88", "93"]}, "88": {"coordinates": [415, 743], "shapes": ["88", "89", "93"]}, "89": {"coordinates": [416, 551], "shapes": ["90", "97"]}, "9": {"coordinates": [716, 867], "shapes": ["4"]}, "90": {"coordinates": [377, 543], "shapes": ["90", "92", "97", "102", "105", "106", "109"]}, "91": {"coordinates": [390, 572], "shapes": ["91", "92", "99", "103", "106"]}, "92": {"coordinates": [394, 534], "shapes": ["94", "97", "100", "102"]}, "93": {"coordinates": [406, 610], "shapes": ["95", "96", "98"]}, "94": {"coordinates": [394, 595], "shapes": ["98", "99", "103"]}, "95": {"coordinates": [391, 505], "shapes": ["100", "102", "104", "105"]}, "96": {"coordinates": [352, 457], "shapes": ["101", "110", "112", "115", "116"]}, "97": {"coordinates": [373, 562], "shapes": ["103", "106"]}, "98": {"coordinates": [371, 476], "shapes": ["104", "110"]}, "99": {"coordinates": [353, 487], "shapes": ["104", "105", "109", "110", "111", "112"]}}}