{"background":"#647e8d","day":"2024-10-25","points":[[332,334],[386,334],[356,300],[406,276],[430,330],[446,268],[470,330],[490,266],[502,332],[528,282],[548,332],[596,308],[610,350],[602,392],[530,384],[558,416],[606,448],[582,484],[530,468],[474,378],[414,384],[362,378],[264,334],[304,368],[228,360],[236,396],[286,414],[652,346],[636,330],[674,322],[704,336],[720,306],[646,308],[686,300],[738,320],[748,284],[770,286],[776,256],[802,244],[760,246],[720,284],[782,216],[804,186],[826,196],[832,154],[846,160],[848,134],[858,138],[308,292],[296,316],[284,328],[242,316],[246,300],[254,276],[222,256],[208,270],[196,286],[166,250],[176,226],[176,208],[150,190],[150,164],[140,196],[122,156],[124,136],[100,112],[102,100],[132,136],[652,360],[628,400],[688,378],[698,412],[664,454],[628,474],[614,502],[602,518],[640,552],[578,570],[518,504],[550,532],[528,558],[480,522],[474,562],[474,584],[530,572],[478,604],[530,602],[428,564],[426,536],[412,500],[446,480],[444,424],[480,452],[380,430],[336,412],[314,460],[350,490],[402,532],[404,572],[444,582],[448,606],[408,604],[370,542],[384,572],[320,502],[342,536],[256,474],[274,532],[214,504],[230,564],[196,540],[232,422],[260,440],[292,572],[240,600],[192,588],[188,626],[250,656],[158,684],[172,706],[164,766],[236,744],[196,814],[210,882],[276,806],[242,904],[270,908],[298,980],[324,956],[324,1044],[264,1032],[254,980],[264,1076],[322,1084],[276,1110],[304,1110],[334,1110],[340,988],[378,954],[372,1030],[356,1074],[354,1110],[396,1092],[412,1050],[428,1116],[396,1140],[426,1150],[396,1158],[434,1172],[396,1174],[362,1168],[358,1146],[426,994],[442,944],[380,886],[440,876],[386,818],[454,802],[440,736],[366,752],[334,854],[320,786],[284,720],[344,594],[302,654],[348,694],[374,630],[414,668],[478,666],[532,670],[514,744],[516,846],[498,910],[472,974],[534,976],[462,1044],[554,1020],[488,1066],[532,1080],[470,1126],[540,1144],[464,1170],[544,1174],[576,992],[600,994],[626,928],[652,854],[684,758],[612,748],[630,628],[674,618]],"shapes":[{"color":"#bc9b88","points":[0,1,2]},{"color":"#bc9b88","points":[3,2,1]},{"color":"#ac9079","points":[4,3,1]},{"color":"#ac9079","points":[5,4,3]},{"color":"#c9a88a","points":[6,5,4]},{"color":"#c9a88a","points":[7,6,5]},{"color":"#b89786","points":[8,7,6]},{"color":"#b89786","points":[9,8,7]},{"color":"#b89786","points":[10,9,8]},{"color":"#ddb19d","points":[11,10,9]},{"color":"#c4ac9f","points":[12,11,10]},{"color":"#371102","points":[13,10,12]},{"color":"#e0b48e","points":[14,13,10]},{"color":"#2b1913","points":[15,16,13]},{"color":"#2e1b18","points":[17,15,16]},{"color":"#200d09","points":[18,17,15]},{"color":"#856251","points":[15,14,13]},{"color":"#4e2b17","points":[8,10,14]},{"color":"#b59a83","points":[19,8,6]},{"color":"#593722","points":[14,8,19]},{"color":"#4b2c21","points":[19,6,4]},{"color":"#5f3d21","points":[20,19,4]},{"color":"#b89e89","points":[1,4,20]},{"color":"#b29079","points":[21,20,1]},{"color":"#735237","points":[0,1,21]},{"color":"#8c5d47","points":[22,23,0]},{"color":"#a58160","points":[21,0,23]},{"color":"#946448","points":[24,23,22]},{"color":"#3c1913","points":[25,23,24]},{"color":"#724e3e","points":[26,23,25]},{"color":"#3b3329","points":[27,28,12]},{"color":"#e1dacc","points":[11,12,28]},{"color":"#bba790","points":[29,27,28]},{"color":"#695038","points":[30,29,27]},{"color":"#e8ddc5","points":[31,30,29]},{"color":"#f3ede3","points":[32,28,29]},{"color":"#f6f4ea","points":[32,28,11]},{"color":"#f8f8f0","points":[33,29,32]},{"color":"#faf6ee","points":[31,33,29]},{"color":"#ccb59b","points":[34,31,30]},{"color":"#c3ac88","points":[35,34,31]},{"color":"#b29e7b","points":[36,35,34]},{"color":"#c4b298","points":[37,36,35]},{"color":"#d6cab5","points":[38,37,36]},{"color":"#ded4c4","points":[39,35,37]},{"color":"#e9e4d7","points":[40,31,35]},{"color":"#f6f9f0","points":[33,40,31]},{"color":"#eeeee7","points":[39,35,40]},{"color":"#e6e3d6","points":[41,37,39]},{"color":"#aea38f","points":[38,41,37]},{"color":"#cec6ae","points":[42,38,41]},{"color":"#d3c3a7","points":[43,42,38]},{"color":"#f1e2d9","points":[44,43,42]},{"color":"#dbccc2","points":[45,44,43]},{"color":"#ece4d8","points":[46,45,44]},{"color":"#f5f0e3","points":[47,46,45]},{"color":"#f0ebe2","points":[48,0,2]},{"color":"#1d1814","points":[49,50,0]},{"color":"#382313","points":[51,52,50]},{"color":"#907966","points":[49,50,52]},{"color":"#d7cdbe","points":[48,0,49]},{"color":"#ece6d8","points":[53,49,52]},{"color":"#f8faef","points":[48,53,49]},{"color":"#f8fdfb","points":[54,52,53]},{"color":"#fafaf1","points":[55,54,52]},{"color":"#e1d0b4","points":[56,52,55]},{"color":"#c4a98c","points":[56,52,51]},{"color":"#cdbb9c","points":[57,55,56]},{"color":"#eee4d1","points":[58,57,55]},{"color":"#f9f4eb","points":[54,55,58]},{"color":"#f7f8ee","points":[59,58,54]},{"color":"#edebdf","points":[60,59,58]},{"color":"#f5eddd","points":[61,60,59]},{"color":"#cfc2ad","points":[62,58,60]},{"color":"#eee5d4","points":[62,58,57]},{"color":"#b9a290","points":[63,60,62]},{"color":"#a48676","points":[64,63,60]},{"color":"#887874","points":[65,64,63]},{"color":"#dccbbd","points":[66,64,65]},{"color":"#f3e6d9","points":[67,64,66]},{"color":"#f3e4d9","points":[61,64,67]},{"color":"#efdfd2","points":[60,64,61]},{"color":"#341709","points":[68,13,12]},{"color":"#301a14","points":[69,16,13]},{"color":"#774a30","points":[68,13,69]},{"color":"#5c2e18","points":[70,68,69]},{"color":"#c3966f","points":[71,69,70]},{"color":"#61351e","points":[72,71,69]},{"color":"#b88362","points":[73,69,16]},{"color":"#ad7c56","points":[72,69,73]},{"color":"#bd8d61","points":[74,16,73]},{"color":"#7b543e","points":[16,74,17]},{"color":"#9f6d44","points":[75,17,74]},{"color":"#9b6340","points":[76,77,75]},{"color":"#a87854","points":[17,75,77]},{"color":"#2c160d","points":[78,79,17]},{"color":"#815a42","points":[77,17,79]},{"color":"#251615","points":[80,78,79]},{"color":"#f2dec8","points":[81,80,78]},{"color":"#e8d2ba","points":[82,81,80]},{"color":"#e8d2ba","points":[83,80,82]},{"color":"#e8d2ba","points":[84,83,80]},{"color":"#fcead9","points":[85,84,83]},{"color":"#e7d0ae","points":[86,85,84]},{"color":"#71574a","points":[77,80,84]},{"color":"#5c3e2d","points":[79,77,80]},{"color":"#6d4e44","points":[86,84,77]},{"color":"#dfc8ab","points":[87,88,82]},{"color":"#e8d2ba","points":[81,82,88]},{"color":"#b49983","points":[89,81,88]},{"color":"#e9d2be","points":[90,89,81]},{"color":"#fff3e3","points":[78,81,90]},{"color":"#1d0a09","points":[91,89,90]},{"color":"#594039","points":[92,91,90]},{"color":"#64412a","points":[19,20,91]},{"color":"#5d463a","points":[93,91,20]},{"color":"#97735b","points":[21,20,93]},{"color":"#0b0204","points":[94,21,93]},{"color":"#381a0f","points":[26,23,94]},{"color":"#755d47","points":[21,23,94]},{"color":"#865944","points":[95,94,26]},{"color":"#080000","points":[96,93,95]},{"color":"#100805","points":[94,95,93]},{"color":"#2e2220","points":[89,93,96]},{"color":"#8f725f","points":[91,89,93]},{"color":"#c3a389","points":[97,88,89]},{"color":"#c9ac90","points":[98,87,97]},{"color":"#dfc8ab","points":[88,97,87]},{"color":"#dfc8ab","points":[99,82,87]},{"color":"#b49588","points":[83,82,99]},{"color":"#b59177","points":[100,83,99]},{"color":"#b99575","points":[85,100,83]},{"color":"#c9ac90","points":[101,99,98]},{"color":"#c9ac90","points":[87,98,99]},{"color":"#c9ac90","points":[100,99,101]},{"color":"#796155","points":[96,89,97]},{"color":"#392116","points":[102,97,96]},{"color":"#1e1312","points":[103,97,102]},{"color":"#0b0000","points":[98,97,103]},{"color":"#2f2016","points":[101,98,103]},{"color":"#7a5e49","points":[19,91,92]},{"color":"#755846","points":[92,14,19]},{"color":"#936a4e","points":[15,92,14]},{"color":"#4b3221","points":[18,15,92]},{"color":"#705e55","points":[78,90,92]},{"color":"#9f7d6a","points":[78,92,18]},{"color":"#47322a","points":[17,78,18]},{"color":"#fdd5a7","points":[104,96,95]},{"color":"#c59f71","points":[105,96,104]},{"color":"#f8e5c7","points":[106,104,95]},{"color":"#e7d7b1","points":[107,106,104]},{"color":"#ca9a70","points":[108,107,106]},{"color":"#d4a77b","points":[109,108,107]},{"color":"#e1b58a","points":[110,109,108]},{"color":"#ddc0a7","points":[111,26,25]},{"color":"#c2a58b","points":[112,26,111]},{"color":"#af9882","points":[95,26,112]},{"color":"#cc9e77","points":[102,96,105]},{"color":"#e7c39a","points":[113,107,105]},{"color":"#dfcba5","points":[104,105,107]},{"color":"#ead1a6","points":[114,109,113]},{"color":"#f6e0bc","points":[107,113,109]},{"color":"#c1915f","points":[110,115,109]},{"color":"#ebcfa6","points":[116,114,115]},{"color":"#e2c69f","points":[109,115,114]},{"color":"#d5ac7e","points":[117,116,114]},{"color":"#d3af7d","points":[118,117,116]},{"color":"#a27645","points":[119,117,118]},{"color":"#9e7352","points":[120,121,119]},{"color":"#b4885d","points":[117,119,121]},{"color":"#33190f","points":[122,121,120]},{"color":"#210f0c","points":[123,124,122]},{"color":"#6c4a38","points":[121,122,124]},{"color":"#120704","points":[125,124,123]},{"color":"#160903","points":[125,124,126]},{"color":"#75482b","points":[127,128,126]},{"color":"#140b09","points":[129,130,127]},{"color":"#170d0c","points":[127,131,130]},{"color":"#1e110a","points":[125,126,131]},{"color":"#110b0a","points":[127,131,126]},{"color":"#150b0b","points":[132,129,130]},{"color":"#191110","points":[133,132,129]},{"color":"#c6ad94","points":[134,135,132]},{"color":"#524436","points":[133,132,135]},{"color":"#bba58c","points":[136,135,133]},{"color":"#1a0f0c","points":[137,138,128]},{"color":"#37271e","points":[129,139,137]},{"color":"#3e271b","points":[140,139,129]},{"color":"#3b2721","points":[140,129,133]},{"color":"#221515","points":[141,142,140]},{"color":"#160c0b","points":[143,140,142]},{"color":"#140e0e","points":[143,140,139]},{"color":"#171110","points":[144,142,143]},{"color":"#1f1211","points":[145,144,142]},{"color":"#654a3c","points":[146,145,144]},{"color":"#7f5a46","points":[147,146,145]},{"color":"#c6b096","points":[148,147,146]},{"color":"#ac8c66","points":[149,148,147]},{"color":"#d8c3ad","points":[150,147,149]},{"color":"#a88c7c","points":[151,150,147]},{"color":"#5e4a3e","points":[145,147,151]},{"color":"#34201c","points":[141,145,151]},{"color":"#1d1411","points":[142,141,145]},{"color":"#050704","points":[152,138,139]},{"color":"#060805","points":[137,139,138]},{"color":"#0a0706","points":[143,152,139]},{"color":"#04080a","points":[153,138,152]},{"color":"#080305","points":[154,153,138]},{"color":"#100605","points":[155,154,153]},{"color":"#0b0505","points":[128,138,154]},{"color":"#0b0404","points":[156,154,155]},{"color":"#090402","points":[157,156,155]},{"color":"#090303","points":[158,157,156]},{"color":"#050100","points":[159,158,156]},{"color":"#241712","points":[160,126,124]},{"color":"#442c1e","points":[128,160,126]},{"color":"#050402","points":[154,128,160]},{"color":"#060201","points":[156,154,160]},{"color":"#321c12","points":[161,159,160]},{"color":"#120b0b","points":[156,160,159]},{"color":"#1a0f0d","points":[161,160,124]},{"color":"#603f28","points":[162,121,124]},{"color":"#bd9362","points":[117,162,121]},{"color":"#d3a679","points":[113,114,117]},{"color":"#92623e","points":[163,105,113]},{"color":"#7a4d31","points":[102,105,163]},{"color":"#714e3c","points":[103,102,163]},{"color":"#673c1d","points":[164,113,163]},{"color":"#c99c6e","points":[117,113,164]},{"color":"#a3764b","points":[162,117,164]},{"color":"#4b3121","points":[165,162,164]},{"color":"#2a1610","points":[161,124,162]},{"color":"#100908","points":[159,162,161]},{"color":"#170f0c","points":[159,162,165]},{"color":"#201210","points":[166,164,165]},{"color":"#331e18","points":[166,163,164]},{"color":"#4c3729","points":[166,163,103]},{"color":"#362114","points":[101,103,166]},{"color":"#432c21","points":[167,166,101]},{"color":"#070104","points":[167,166,165]},{"color":"#100606","points":[159,165,167]},{"color":"#080706","points":[158,159,167]},{"color":"#594334","points":[100,101,167]},{"color":"#1d100b","points":[168,100,167]},{"color":"#060001","points":[168,100,85]},{"color":"#1a0c03","points":[158,167,168]},{"color":"#4e3226","points":[169,86,168]},{"color":"#040203","points":[85,168,86]},{"color":"#0f0705","points":[170,168,158]},{"color":"#170a04","points":[170,168,169]},{"color":"#190802","points":[170,158,157]},{"color":"#4b2c1f","points":[171,170,157]},{"color":"#2c1d15","points":[172,155,171]},{"color":"#382417","points":[157,171,155]},{"color":"#5e4b42","points":[153,155,172]},{"color":"#161210","points":[173,172,153]},{"color":"#221008","points":[174,173,172]},{"color":"#201611","points":[175,174,173]},{"color":"#080806","points":[176,175,174]},{"color":"#241d1c","points":[177,176,175]},{"color":"#201817","points":[178,177,176]},{"color":"#2c1a13","points":[179,178,177]},{"color":"#a18171","points":[180,179,178]},{"color":"#402923","points":[181,180,179]},{"color":"#b59a84","points":[182,181,180]},{"color":"#3f2110","points":[183,174,176]},{"color":"#855b34","points":[184,185,183]},{"color":"#7e502b","points":[174,183,185]},{"color":"#170c0b","points":[172,185,174]},{"color":"#130806","points":[186,172,185]},{"color":"#3d2b25","points":[171,186,172]},{"color":"#a47254","points":[187,188,186]},{"color":"#050402","points":[171,186,188]},{"color":"#150d09","points":[170,171,188]},{"color":"#3a211a","points":[170,188,169]},{"color":"#7b523f","points":[189,187,188]},{"color":"#a97a50","points":[190,189,187]},{"color":"#e4bf95","points":[76,190,189]},{"color":"#ac7146","points":[77,76,189]},{"color":"#2b1911","points":[86,169,77]},{"color":"#906546","points":[189,77,169]},{"color":"#603d32","points":[189,188,169]}],"title":"Earthshaker - Friday, October 25, 2024"}